[{"code":"7301","mask":"+_ (___) ___-__-__"},{"code":"73012","mask":"+_ (____) __-__-__"},{"code":"730131","mask":"+_ (_____) _-__-__"},{"code":"730133","mask":"+_ (_____) _-__-__"},{"code":"730134","mask":"+_ (_____) _-__-__"},{"code":"730135","mask":"+_ (_____) _-__-__"},{"code":"730140","mask":"+_ (_____) _-__-__"},{"code":"730141","mask":"+_ (_____) _-__-__"},{"code":"730142","mask":"+_ (_____) _-__-__"},{"code":"730143","mask":"+_ (_____) _-__-__"},{"code":"730144","mask":"+_ (_____) _-__-__"},{"code":"730145","mask":"+_ (_____) _-__-__"},{"code":"730146","mask":"+_ (_____) _-__-__"},{"code":"730148","mask":"+_ (_____) _-__-__"},{"code":"730149","mask":"+_ (_____) _-__-__"},{"code":"7302","mask":"+_ (___) ___-__-__"},{"code":"73022","mask":"+_ (____) __-__-__"},{"code":"730230","mask":"+_ (_____) _-__-__"},{"code":"730231","mask":"+_ (_____) _-__-__"},{"code":"730232","mask":"+_ (_____) _-__-__"},{"code":"730233","mask":"+_ (_____) _-__-__"},{"code":"730234","mask":"+_ (_____) _-__-__"},{"code":"730235","mask":"+_ (_____) _-__-__"},{"code":"730237","mask":"+_ (_____) _-__-__"},{"code":"730238","mask":"+_ (_____) _-__-__"},{"code":"730239","mask":"+_ (_____) _-__-__"},{"code":"730242","mask":"+_ (_____) _-__-__"},{"code":"730243","mask":"+_ (_____) _-__-__"},{"code":"730244","mask":"+_ (_____) _-__-__"},{"code":"730245","mask":"+_ (_____) _-__-__"},{"code":"730246","mask":"+_ (_____) _-__-__"},{"code":"730249","mask":"+_ (_____) _-__-__"},{"code":"730251","mask":"+_ (_____) _-__-__"},{"code":"730255","mask":"+_ (_____) _-__-__"},{"code":"730256","mask":"+_ (_____) _-__-__"},{"code":"730261","mask":"+_ (_____) _-__-__"},{"code":"730262","mask":"+_ (_____) _-__-__"},{"code":"730264","mask":"+_ (_____) _-__-__"},{"code":"730265","mask":"+_ (_____) _-__-__"},{"code":"730266","mask":"+_ (_____) _-__-__"},{"code":"7341","mask":"+_ (___) ___-__-__"},{"code":"73412","mask":"+_ (____) __-__-__"},{"code":"734130","mask":"+_ (_____) _-__-__"},{"code":"734132","mask":"+_ (_____) _-__-__"},{"code":"734133","mask":"+_ (_____) _-__-__"},{"code":"734134","mask":"+_ (_____) _-__-__"},{"code":"734136","mask":"+_ (_____) _-__-__"},{"code":"734138","mask":"+_ (_____) _-__-__"},{"code":"734139","mask":"+_ (_____) _-__-__"},{"code":"734141","mask":"+_ (_____) _-__-__"},{"code":"734145","mask":"+_ (_____) _-__-__"},{"code":"734147","mask":"+_ (_____) _-__-__"},{"code":"734150","mask":"+_ (_____) _-__-__"},{"code":"734151","mask":"+_ (_____) _-__-__"},{"code":"734152","mask":"+_ (_____) _-__-__"},{"code":"734153","mask":"+_ (_____) _-__-__"},{"code":"734154","mask":"+_ (_____) _-__-__"},{"code":"734155","mask":"+_ (_____) _-__-__"},{"code":"734157","mask":"+_ (_____) _-__-__"},{"code":"734158","mask":"+_ (_____) _-__-__"},{"code":"734159","mask":"+_ (_____) _-__-__"},{"code":"734161","mask":"+_ (_____) _-__-__"},{"code":"734162","mask":"+_ (_____) _-__-__"},{"code":"734163","mask":"+_ (_____) _-__-__"},{"code":"734164","mask":"+_ (_____) _-__-__"},{"code":"734166","mask":"+_ (_____) _-__-__"},{"code":"7342","mask":"+_ (___) ___-__-__"},{"code":"73422","mask":"+_ (___) ___-__-__"},{"code":"734240","mask":"+_ (_____) _-__-__"},{"code":"734241","mask":"+_ (_____) _-__-__"},{"code":"734242","mask":"+_ (____) __-__-__"},{"code":"734243","mask":"+_ (_____) _-__-__"},{"code":"734244","mask":"+_ (_____) _-__-__"},{"code":"734248","mask":"+_ (_____) _-__-__"},{"code":"734249","mask":"+_ (_____) _-__-__"},{"code":"734250","mask":"+_ (_____) _-__-__"},{"code":"734251","mask":"+_ (_____) _-__-__"},{"code":"734252","mask":"+_ (_____) _-__-__"},{"code":"734253","mask":"+_ (_____) _-__-__"},{"code":"734254","mask":"+_ (_____) _-__-__"},{"code":"734255","mask":"+_ (_____) _-__-__"},{"code":"734256","mask":"+_ (_____) _-__-__"},{"code":"734257","mask":"+_ (_____) _-__-__"},{"code":"734258","mask":"+_ (_____) _-__-__"},{"code":"734259","mask":"+_ (_____) _-__-__"},{"code":"734260","mask":"+_ (_____) _-__-__"},{"code":"734261","mask":"+_ (_____) _-__-__"},{"code":"734262","mask":"+_ (_____) _-__-__"},{"code":"734263","mask":"+_ (_____) _-__-__"},{"code":"734265","mask":"+_ (_____) _-__-__"},{"code":"734266","mask":"+_ (_____) _-__-__"},{"code":"734268","mask":"+_ (_____) _-__-__"},{"code":"734269","mask":"+_ (_____) _-__-__"},{"code":"734271","mask":"+_ (_____) _-__-__"},{"code":"734272","mask":"+_ (_____) _-__-__"},{"code":"734273","mask":"+_ (_____) _-__-__"},{"code":"734274","mask":"+_ (_____) _-__-__"},{"code":"734275","mask":"+_ (_____) _-__-__"},{"code":"734276","mask":"+_ (_____) _-__-__"},{"code":"734277","mask":"+_ (_____) _-__-__"},{"code":"734278","mask":"+_ (_____) _-__-__"},{"code":"734279","mask":"+_ (_____) _-__-__"},{"code":"734291","mask":"+_ (_____) _-__-__"},{"code":"734296","mask":"+_ (_____) _-__-__"},{"code":"734297","mask":"+_ (_____) _-__-__"},{"code":"7343","mask":"+_ (___) ___-__-__"},{"code":"734341","mask":"+_ (_____) _-__-__"},{"code":"734343","mask":"+_ (_____) _-__-__"},{"code":"734344","mask":"+_ (_____) _-__-__"},{"code":"734345","mask":"+_ (_____) _-__-__"},{"code":"734346","mask":"+_ (_____) _-__-__"},{"code":"734347","mask":"+_ (_____) _-__-__"},{"code":"734349","mask":"+_ (_____) _-__-__"},{"code":"73435","mask":"+_ (____) __-__-__"},{"code":"734350","mask":"+_ (_____) _-__-__"},{"code":"734355","mask":"+_ (_____) _-__-__"},{"code":"734356","mask":"+_ (_____) _-__-__"},{"code":"734357","mask":"+_ (_____) _-__-__"},{"code":"734358","mask":"+_ (_____) _-__-__"},{"code":"734360","mask":"+_ (_____) _-__-__"},{"code":"734361","mask":"+_ (_____) _-__-__"},{"code":"734362","mask":"+_ (_____) _-__-__"},{"code":"734363","mask":"+_ (_____) _-__-__"},{"code":"734364","mask":"+_ (_____) _-__-__"},{"code":"734365","mask":"+_ (_____) _-__-__"},{"code":"734367","mask":"+_ (_____) _-__-__"},{"code":"734368","mask":"+_ (_____) _-__-__"},{"code":"734369","mask":"+_ (_____) _-__-__"},{"code":"734370","mask":"+_ (_____) _-__-__"},{"code":"734371","mask":"+_ (_____) _-__-__"},{"code":"734373","mask":"+_ (_____) _-__-__"},{"code":"734374","mask":"+_ (_____) _-__-__"},{"code":"734375","mask":"+_ (_____) _-__-__"},{"code":"734376","mask":"+_ (_____) _-__-__"},{"code":"734377","mask":"+_ (_____) _-__-__"},{"code":"734391","mask":"+_ (_____) _-__-__"},{"code":"734392","mask":"+_ (____) __-__-__"},{"code":"734394","mask":"+_ (_____) _-__-__"},{"code":"734395","mask":"+_ (_____) _-__-__"},{"code":"734396","mask":"+_ (____) __-__-__"},{"code":"734397","mask":"+_ (_____) _-__-__"},{"code":"7345","mask":"+_ (___) ___-__-__"},{"code":"73452","mask":"+_ (____) __-__-__"},{"code":"734531","mask":"+_ (_____) _-__-__"},{"code":"734533","mask":"+_ (_____) _-__-__"},{"code":"734535","mask":"+_ (_____) _-__-__"},{"code":"734537","mask":"+_ (_____) _-__-__"},{"code":"734541","mask":"+_ (_____) _-__-__"},{"code":"734542","mask":"+_ (_____) _-__-__"},{"code":"734543","mask":"+_ (_____) _-__-__"},{"code":"734544","mask":"+_ (_____) _-__-__"},{"code":"734545","mask":"+_ (_____) _-__-__"},{"code":"734546","mask":"+_ (_____) _-__-__"},{"code":"734547","mask":"+_ (_____) _-__-__"},{"code":"734550","mask":"+_ (_____) _-__-__"},{"code":"734551","mask":"+_ (_____) _-__-__"},{"code":"734553","mask":"+_ (_____) _-__-__"},{"code":"734554","mask":"+_ (_____) _-__-__"},{"code":"734555","mask":"+_ (_____) _-__-__"},{"code":"734556","mask":"+_ (_____) _-__-__"},{"code":"734557","mask":"+_ (_____) _-__-__"},{"code":"7346","mask":"+_ (___) ___-__-__"},{"code":"73462","mask":"+_ (____) __-__-__"},{"code":"73466","mask":"+_ (____) __-__-__"},{"code":"734667","mask":"+_ (_____) _-__-__"},{"code":"734668","mask":"+_ (_____) _-__-__"},{"code":"734669","mask":"+_ (_____) _-__-__"},{"code":"734670","mask":"+_ (_____) _-__-__"},{"code":"734672","mask":"+_ (_____) _-__-__"},{"code":"734674","mask":"+_ (_____) _-__-__"},{"code":"734675","mask":"+_ (_____) _-__-__"},{"code":"734676","mask":"+_ (_____) _-__-__"},{"code":"734677","mask":"+_ (_____) _-__-__"},{"code":"734678","mask":"+_ (_____) _-__-__"},{"code":"7347","mask":"+_ (___) ___-__-__"},{"code":"73472","mask":"+_ (___) ___-__-__"},{"code":"73473","mask":"+_ (____) __-__-__"},{"code":"734739","mask":"+_ (_____) _-__-__"},{"code":"734740","mask":"+_ (_____) _-__-__"},{"code":"734741","mask":"+_ (_____) _-__-__"},{"code":"734742","mask":"+_ (_____) _-__-__"},{"code":"734743","mask":"+_ (_____) _-__-__"},{"code":"734744","mask":"+_ (_____) _-__-__"},{"code":"734745","mask":"+_ (_____) _-__-__"},{"code":"734746","mask":"+_ (_____) _-__-__"},{"code":"734747","mask":"+_ (_____) _-__-__"},{"code":"734748","mask":"+_ (_____) _-__-__"},{"code":"734749","mask":"+_ (_____) _-__-__"},{"code":"734750","mask":"+_ (_____) _-__-__"},{"code":"734751","mask":"+_ (_____) _-__-__"},{"code":"734752","mask":"+_ (_____) _-__-__"},{"code":"734754","mask":"+_ (_____) _-__-__"},{"code":"734756","mask":"+_ (_____) _-__-__"},{"code":"734757","mask":"+_ (_____) _-__-__"},{"code":"734758","mask":"+_ (_____) _-__-__"},{"code":"734759","mask":"+_ (_____) _-__-__"},{"code":"734760","mask":"+_ (_____) _-__-__"},{"code":"734761","mask":"+_ (_____) _-__-__"},{"code":"734762","mask":"+_ (_____) _-__-__"},{"code":"734763","mask":"+_ (_____) _-__-__"},{"code":"734764","mask":"+_ (_____) _-__-__"},{"code":"734765","mask":"+_ (_____) _-__-__"},{"code":"734766","mask":"+_ (_____) _-__-__"},{"code":"734767","mask":"+_ (_____) _-__-__"},{"code":"734768","mask":"+_ (_____) _-__-__"},{"code":"734769","mask":"+_ (_____) _-__-__"},{"code":"734770","mask":"+_ (_____) _-__-__"},{"code":"734771","mask":"+_ (_____) _-__-__"},{"code":"734772","mask":"+_ (_____) _-__-__"},{"code":"734773","mask":"+_ (_____) _-__-__"},{"code":"734774","mask":"+_ (_____) _-__-__"},{"code":"734775","mask":"+_ (_____) _-__-__"},{"code":"734776","mask":"+_ (_____) _-__-__"},{"code":"734777","mask":"+_ (_____) _-__-__"},{"code":"734779","mask":"+_ (_____) _-__-__"},{"code":"734791","mask":"+_ (_____) _-__-__"},{"code":"734792","mask":"+_ (_____) _-__-__"},{"code":"734794","mask":"+_ (_____) _-__-__"},{"code":"734795","mask":"+_ (_____) _-__-__"},{"code":"734796","mask":"+_ (_____) _-__-__"},{"code":"734797","mask":"+_ (_____) _-__-__"},{"code":"734798","mask":"+_ (_____) _-__-__"},{"code":"7349","mask":"+_ (___) ___-__-__"},{"code":"7351","mask":"+_ (___) ___-__-__"},{"code":"73512","mask":"+_ (___) ___-__-__"},{"code":"735131","mask":"+_ (_____) _-__-__"},{"code":"735132","mask":"+_ (____) __-__-__"},{"code":"735133","mask":"+_ (_____) _-__-__"},{"code":"735134","mask":"+_ (_____) _-__-__"},{"code":"735135","mask":"+_ (____) __-__-__"},{"code":"735136","mask":"+_ (____) __-__-__"},{"code":"735138","mask":"+_ (_____) _-__-__"},{"code":"735139","mask":"+_ (_____) _-__-__"},{"code":"735140","mask":"+_ (_____) _-__-__"},{"code":"735141","mask":"+_ (_____) _-__-__"},{"code":"735142","mask":"+_ (_____) _-__-__"},{"code":"735143","mask":"+_ (_____) _-__-__"},{"code":"735144","mask":"+_ (_____) _-__-__"},{"code":"735145","mask":"+_ (_____) _-__-__"},{"code":"735146","mask":"+_ (_____) _-__-__"},{"code":"735147","mask":"+_ (_____) _-__-__"},{"code":"735148","mask":"+_ (_____) _-__-__"},{"code":"735149","mask":"+_ (_____) _-__-__"},{"code":"735150","mask":"+_ (_____) _-__-__"},{"code":"735151","mask":"+_ (_____) _-__-__"},{"code":"735152","mask":"+_ (_____) _-__-__"},{"code":"735153","mask":"+_ (_____) _-__-__"},{"code":"735154","mask":"+_ (_____) _-__-__"},{"code":"735155","mask":"+_ (_____) _-__-__"},{"code":"735156","mask":"+_ (_____) _-__-__"},{"code":"735157","mask":"+_ (_____) _-__-__"},{"code":"735158","mask":"+_ (_____) _-__-__"},{"code":"735159","mask":"+_ (_____) _-__-__"},{"code":"735160","mask":"+_ (_____) _-__-__"},{"code":"735161","mask":"+_ (_____) _-__-__"},{"code":"735163","mask":"+_ (_____) _-__-__"},{"code":"735164","mask":"+_ (_____) _-__-__"},{"code":"735165","mask":"+_ (_____) _-__-__"},{"code":"735166","mask":"+_ (_____) _-__-__"},{"code":"735167","mask":"+_ (_____) _-__-__"},{"code":"735168","mask":"+_ (_____) _-__-__"},{"code":"735169","mask":"+_ (_____) _-__-__"},{"code":"7352","mask":"+_ (___) ___-__-__"},{"code":"73522","mask":"+_ (____) __-__-__"},{"code":"735230","mask":"+_ (_____) _-__-__"},{"code":"735231","mask":"+_ (_____) _-__-__"},{"code":"735232","mask":"+_ (_____) _-__-__"},{"code":"735233","mask":"+_ (_____) _-__-__"},{"code":"735234","mask":"+_ (_____) _-__-__"},{"code":"735235","mask":"+_ (_____) _-__-__"},{"code":"735236","mask":"+_ (_____) _-__-__"},{"code":"735237","mask":"+_ (_____) _-__-__"},{"code":"735238","mask":"+_ (_____) _-__-__"},{"code":"735239","mask":"+_ (_____) _-__-__"},{"code":"735240","mask":"+_ (_____) _-__-__"},{"code":"735241","mask":"+_ (_____) _-__-__"},{"code":"735242","mask":"+_ (_____) _-__-__"},{"code":"735243","mask":"+_ (_____) _-__-__"},{"code":"735244","mask":"+_ (_____) _-__-__"},{"code":"735245","mask":"+_ (_____) _-__-__"},{"code":"735247","mask":"+_ (_____) _-__-__"},{"code":"735248","mask":"+_ (_____) _-__-__"},{"code":"735249","mask":"+_ (_____) _-__-__"},{"code":"735251","mask":"+_ (_____) _-__-__"},{"code":"735252","mask":"+_ (_____) _-__-__"},{"code":"735253","mask":"+_ (_____) _-__-__"},{"code":"735256","mask":"+_ (_____) _-__-__"},{"code":"735257","mask":"+_ (_____) _-__-__"},{"code":"7353","mask":"+_ (___) ___-__-__"},{"code":"73532","mask":"+_ (____) __-__-__"},{"code":"735330","mask":"+_ (_____) _-__-__"},{"code":"735331","mask":"+_ (_____) _-__-__"},{"code":"735332","mask":"+_ (_____) _-__-__"},{"code":"735333","mask":"+_ (_____) _-__-__"},{"code":"735334","mask":"+_ (_____) _-__-__"},{"code":"735335","mask":"+_ (_____) _-__-__"},{"code":"735336","mask":"+_ (_____) _-__-__"},{"code":"735337","mask":"+_ (_____) _-__-__"},{"code":"735338","mask":"+_ (_____) _-__-__"},{"code":"735339","mask":"+_ (_____) _-__-__"},{"code":"735341","mask":"+_ (_____) _-__-__"},{"code":"735342","mask":"+_ (_____) _-__-__"},{"code":"735344","mask":"+_ (_____) _-__-__"},{"code":"735345","mask":"+_ (_____) _-__-__"},{"code":"735346","mask":"+_ (_____) _-__-__"},{"code":"735347","mask":"+_ (_____) _-__-__"},{"code":"735348","mask":"+_ (_____) _-__-__"},{"code":"735349","mask":"+_ (_____) _-__-__"},{"code":"735351","mask":"+_ (_____) _-__-__"},{"code":"735352","mask":"+_ (_____) _-__-__"},{"code":"735354","mask":"+_ (_____) _-__-__"},{"code":"735355","mask":"+_ (_____) _-__-__"},{"code":"735356","mask":"+_ (_____) _-__-__"},{"code":"735357","mask":"+_ (_____) _-__-__"},{"code":"735358","mask":"+_ (_____) _-__-__"},{"code":"735359","mask":"+_ (_____) _-__-__"},{"code":"735361","mask":"+_ (_____) _-__-__"},{"code":"735362","mask":"+_ (_____) _-__-__"},{"code":"735363","mask":"+_ (_____) _-__-__"},{"code":"735364","mask":"+_ (_____) _-__-__"},{"code":"735365","mask":"+_ (_____) _-__-__"},{"code":"735366","mask":"+_ (_____) _-__-__"},{"code":"735367","mask":"+_ (_____) _-__-__"},{"code":"735368","mask":"+_ (_____) _-__-__"},{"code":"735372","mask":"+_ (____) __-__-__"},{"code":"735376","mask":"+_ (____) __-__-__"},{"code":"735379","mask":"+_ (_____) _-__-__"},{"code":"7381","mask":"+_ (___) ___-__-__"},{"code":"73812","mask":"+_ (____) __-__-__"},{"code":"738141","mask":"+_ (_____) _-__-__"},{"code":"738150","mask":"+_ (_____) _-__-__"},{"code":"738151","mask":"+_ (_____) _-__-__"},{"code":"738152","mask":"+_ (_____) _-__-__"},{"code":"738153","mask":"+_ (_____) _-__-__"},{"code":"738154","mask":"+_ (_____) _-__-__"},{"code":"738155","mask":"+_ (_____) _-__-__"},{"code":"738156","mask":"+_ (_____) _-__-__"},{"code":"738157","mask":"+_ (_____) _-__-__"},{"code":"738158","mask":"+_ (_____) _-__-__"},{"code":"738159","mask":"+_ (_____) _-__-__"},{"code":"738160","mask":"+_ (_____) _-__-__"},{"code":"738161","mask":"+_ (_____) _-__-__"},{"code":"738162","mask":"+_ (_____) _-__-__"},{"code":"738163","mask":"+_ (_____) _-__-__"},{"code":"738164","mask":"+_ (_____) _-__-__"},{"code":"738165","mask":"+_ (_____) _-__-__"},{"code":"738166","mask":"+_ (_____) _-__-__"},{"code":"738167","mask":"+_ (_____) _-__-__"},{"code":"738168","mask":"+_ (_____) _-__-__"},{"code":"738169","mask":"+_ (_____) _-__-__"},{"code":"738170","mask":"+_ (_____) _-__-__"},{"code":"738171","mask":"+_ (_____) _-__-__"},{"code":"738172","mask":"+_ (_____) _-__-__"},{"code":"738173","mask":"+_ (_____) _-__-__"},{"code":"738174","mask":"+_ (_____) _-__-__"},{"code":"738175","mask":"+_ (_____) _-__-__"},{"code":"738176","mask":"+_ (_____) _-__-__"},{"code":"738177","mask":"+_ (_____) _-__-__"},{"code":"738178","mask":"+_ (_____) _-__-__"},{"code":"738179","mask":"+_ (_____) _-__-__"},{"code":"7382","mask":"+_ (___) ___-__-__"},{"code":"73822","mask":"+_ (____) __-__-__"},{"code":"738241","mask":"+_ (_____) _-__-__"},{"code":"738244","mask":"+_ (_____) _-__-__"},{"code":"738245","mask":"+_ (_____) _-__-__"},{"code":"738246","mask":"+_ (_____) _-__-__"},{"code":"738247","mask":"+_ (_____) _-__-__"},{"code":"738249","mask":"+_ (_____) _-__-__"},{"code":"738251","mask":"+_ (_____) _-__-__"},{"code":"738252","mask":"+_ (_____) _-__-__"},{"code":"738253","mask":"+_ (_____) _-__-__"},{"code":"738254","mask":"+_ (_____) _-__-__"},{"code":"738255","mask":"+_ (_____) _-__-__"},{"code":"738256","mask":"+_ (_____) _-__-__"},{"code":"738257","mask":"+_ (_____) _-__-__"},{"code":"738258","mask":"+_ (_____) _-__-__"},{"code":"738259","mask":"+_ (_____) _-__-__"},{"code":"7383","mask":"+_ (___) ___-__-__"},{"code":"738340","mask":"+_ (_____) _-__-__"},{"code":"738341","mask":"+_ (_____) _-__-__"},{"code":"738343","mask":"+_ (_____) _-__-__"},{"code":"738345","mask":"+_ (_____) _-__-__"},{"code":"738346","mask":"+_ (_____) _-__-__"},{"code":"738347","mask":"+_ (_____) _-__-__"},{"code":"738348","mask":"+_ (_____) _-__-__"},{"code":"738349","mask":"+_ (_____) _-__-__"},{"code":"738350","mask":"+_ (_____) _-__-__"},{"code":"738351","mask":"+_ (_____) _-__-__"},{"code":"738352","mask":"+_ (_____) _-__-__"},{"code":"738353","mask":"+_ (_____) _-__-__"},{"code":"738354","mask":"+_ (_____) _-__-__"},{"code":"738355","mask":"+_ (_____) _-__-__"},{"code":"738356","mask":"+_ (_____) _-__-__"},{"code":"738357","mask":"+_ (_____) _-__-__"},{"code":"738358","mask":"+_ (_____) _-__-__"},{"code":"738359","mask":"+_ (_____) _-__-__"},{"code":"738360","mask":"+_ (_____) _-__-__"},{"code":"738361","mask":"+_ (_____) _-__-__"},{"code":"738362","mask":"+_ (_____) _-__-__"},{"code":"738363","mask":"+_ (_____) _-__-__"},{"code":"738364","mask":"+_ (_____) _-__-__"},{"code":"738365","mask":"+_ (_____) _-__-__"},{"code":"738366","mask":"+_ (_____) _-__-__"},{"code":"738367","mask":"+_ (_____) _-__-__"},{"code":"738368","mask":"+_ (_____) _-__-__"},{"code":"738369","mask":"+_ (_____) _-__-__"},{"code":"738371","mask":"+_ (_____) _-__-__"},{"code":"738372","mask":"+_ (_____) _-__-__"},{"code":"738373","mask":"+_ (_____) _-__-__"},{"code":"7384","mask":"+_ (___) ___-__-__"},{"code":"73842","mask":"+_ (____) __-__-__"},{"code":"73843","mask":"+_ (____) __-__-__"},{"code":"738441","mask":"+_ (_____) _-__-__"},{"code":"738442","mask":"+_ (_____) _-__-__"},{"code":"738443","mask":"+_ (_____) _-__-__"},{"code":"738444","mask":"+_ (_____) _-__-__"},{"code":"738445","mask":"+_ (_____) _-__-__"},{"code":"738446","mask":"+_ (_____) _-__-__"},{"code":"738447","mask":"+_ (_____) _-__-__"},{"code":"738448","mask":"+_ (_____) _-__-__"},{"code":"738449","mask":"+_ (_____) _-__-__"},{"code":"738451","mask":"+_ (_____) _-__-__"},{"code":"738452","mask":"+_ (_____) _-__-__"},{"code":"738453","mask":"+_ (_____) _-__-__"},{"code":"738454","mask":"+_ (_____) _-__-__"},{"code":"738455","mask":"+_ (_____) _-__-__"},{"code":"738456","mask":"+_ (_____) _-__-__"},{"code":"738459","mask":"+_ (_____) _-__-__"},{"code":"738463","mask":"+_ (_____) _-__-__"},{"code":"738464","mask":"+_ (_____) _-__-__"},{"code":"738471","mask":"+_ (_____) _-__-__"},{"code":"738473","mask":"+_ (_____) _-__-__"},{"code":"738474","mask":"+_ (_____) _-__-__"},{"code":"738475","mask":"+_ (_____) _-__-__"},{"code":"7385","mask":"+_ (___) ___-__-__"},{"code":"73852","mask":"+_ (____) __-__-__"},{"code":"738530","mask":"+_ (_____) _-__-__"},{"code":"738531","mask":"+_ (_____) _-__-__"},{"code":"738532","mask":"+_ (_____) _-__-__"},{"code":"738533","mask":"+_ (_____) _-__-__"},{"code":"738534","mask":"+_ (_____) _-__-__"},{"code":"738535","mask":"+_ (_____) _-__-__"},{"code":"738536","mask":"+_ (_____) _-__-__"},{"code":"738537","mask":"+_ (_____) _-__-__"},{"code":"738539","mask":"+_ (_____) _-__-__"},{"code":"73854","mask":"+_ (____) __-__-__"},{"code":"738550","mask":"+_ (_____) _-__-__"},{"code":"738552","mask":"+_ (_____) _-__-__"},{"code":"738553","mask":"+_ (_____) _-__-__"},{"code":"738554","mask":"+_ (_____) _-__-__"},{"code":"738555","mask":"+_ (_____) _-__-__"},{"code":"738556","mask":"+_ (_____) _-__-__"},{"code":"738557","mask":"+_ (_____) _-__-__"},{"code":"738558","mask":"+_ (_____) _-__-__"},{"code":"738559","mask":"+_ (_____) _-__-__"},{"code":"738560","mask":"+_ (_____) _-__-__"},{"code":"738561","mask":"+_ (_____) _-__-__"},{"code":"738562","mask":"+_ (_____) _-__-__"},{"code":"738563","mask":"+_ (_____) _-__-__"},{"code":"738564","mask":"+_ (_____) _-__-__"},{"code":"738565","mask":"+_ (_____) _-__-__"},{"code":"738566","mask":"+_ (_____) _-__-__"},{"code":"738567","mask":"+_ (_____) _-__-__"},{"code":"738568","mask":"+_ (_____) _-__-__"},{"code":"738569","mask":"+_ (_____) _-__-__"},{"code":"738570","mask":"+_ (_____) _-__-__"},{"code":"738571","mask":"+_ (_____) _-__-__"},{"code":"738572","mask":"+_ (_____) _-__-__"},{"code":"738573","mask":"+_ (_____) _-__-__"},{"code":"738574","mask":"+_ (_____) _-__-__"},{"code":"738575","mask":"+_ (_____) _-__-__"},{"code":"738576","mask":"+_ (_____) _-__-__"},{"code":"738577","mask":"+_ (_____) _-__-__"},{"code":"738578","mask":"+_ (_____) _-__-__"},{"code":"738579","mask":"+_ (_____) _-__-__"},{"code":"738590","mask":"+_ (_____) _-__-__"},{"code":"738591","mask":"+_ (_____) _-__-__"},{"code":"738592","mask":"+_ (_____) _-__-__"},{"code":"738593","mask":"+_ (_____) _-__-__"},{"code":"738594","mask":"+_ (_____) _-__-__"},{"code":"738595","mask":"+_ (_____) _-__-__"},{"code":"738596","mask":"+_ (_____) _-__-__"},{"code":"738597","mask":"+_ (_____) _-__-__"},{"code":"738598","mask":"+_ (_____) _-__-__"},{"code":"738599","mask":"+_ (_____) _-__-__"},{"code":"7388","mask":"+_ (___) ___-__-__"},{"code":"738840","mask":"+_ (_____) _-__-__"},{"code":"738843","mask":"+_ (_____) _-__-__"},{"code":"738844","mask":"+_ (_____) _-__-__"},{"code":"738845","mask":"+_ (_____) _-__-__"},{"code":"738847","mask":"+_ (_____) _-__-__"},{"code":"738849","mask":"+_ (_____) _-__-__"},{"code":"7390","mask":"+_ (___) ___-__-__"},{"code":"739031","mask":"+_ (_____) _-__-__"},{"code":"739032","mask":"+_ (_____) _-__-__"},{"code":"739033","mask":"+_ (_____) _-__-__"},{"code":"739034","mask":"+_ (_____) _-__-__"},{"code":"739035","mask":"+_ (_____) _-__-__"},{"code":"739036","mask":"+_ (_____) _-__-__"},{"code":"739041","mask":"+_ (_____) _-__-__"},{"code":"739042","mask":"+_ (_____) _-__-__"},{"code":"739044","mask":"+_ (_____) _-__-__"},{"code":"739045","mask":"+_ (_____) _-__-__"},{"code":"739046","mask":"+_ (_____) _-__-__"},{"code":"739047","mask":"+_ (_____) _-__-__"},{"code":"7391","mask":"+_ (___) ___-__-__"},{"code":"73912","mask":"+_ (___) ___-__-__"},{"code":"739131","mask":"+_ (_____) _-__-__"},{"code":"739132","mask":"+_ (_____) _-__-__"},{"code":"739133","mask":"+_ (_____) _-__-__"},{"code":"739134","mask":"+_ (_____) _-__-__"},{"code":"739135","mask":"+_ (_____) _-__-__"},{"code":"739136","mask":"+_ (_____) _-__-__"},{"code":"739137","mask":"+_ (_____) _-__-__"},{"code":"739138","mask":"+_ (_____) _-__-__"},{"code":"739139","mask":"+_ (_____) _-__-__"},{"code":"739140","mask":"+_ (_____) _-__-__"},{"code":"739142","mask":"+_ (_____) _-__-__"},{"code":"739143","mask":"+_ (_____) _-__-__"},{"code":"739144","mask":"+_ (_____) _-__-__"},{"code":"739145","mask":"+_ (_____) _-__-__"},{"code":"739146","mask":"+_ (_____) _-__-__"},{"code":"739147","mask":"+_ (_____) _-__-__"},{"code":"739148","mask":"+_ (_____) _-__-__"},{"code":"739149","mask":"+_ (_____) _-__-__"},{"code":"739150","mask":"+_ (_____) _-__-__"},{"code":"739151","mask":"+_ (_____) _-__-__"},{"code":"739153","mask":"+_ (_____) _-__-__"},{"code":"739154","mask":"+_ (_____) _-__-__"},{"code":"739155","mask":"+_ (_____) _-__-__"},{"code":"739156","mask":"+_ (_____) _-__-__"},{"code":"739157","mask":"+_ (_____) _-__-__"},{"code":"739158","mask":"+_ (_____) _-__-__"},{"code":"739159","mask":"+_ (_____) _-__-__"},{"code":"739161","mask":"+_ (_____) _-__-__"},{"code":"739162","mask":"+_ (_____) _-__-__"},{"code":"739163","mask":"+_ (_____) _-__-__"},{"code":"739164","mask":"+_ (_____) _-__-__"},{"code":"739165","mask":"+_ (_____) _-__-__"},{"code":"739167","mask":"+_ (_____) _-__-__"},{"code":"739168","mask":"+_ (_____) _-__-__"},{"code":"739169","mask":"+_ (_____) _-__-__"},{"code":"739170","mask":"+_ (_____) _-__-__"},{"code":"739171","mask":"+_ (_____) _-__-__"},{"code":"739173","mask":"+_ (_____) _-__-__"},{"code":"739174","mask":"+_ (_____) _-__-__"},{"code":"739175","mask":"+_ (_____) _-__-__"},{"code":"739195","mask":"+_ (_____) _-__-__"},{"code":"739197","mask":"+_ (_____) _-__-__"},{"code":"7394","mask":"+_ (___) ___-__-__"},{"code":"7395","mask":"+_ (___) ___-__-__"},{"code":"73952","mask":"+_ (____) __-__-__"},{"code":"73953","mask":"+_ (____) __-__-__"},{"code":"739535","mask":"+_ (_____) _-__-__"},{"code":"739543","mask":"+_ (_____) _-__-__"},{"code":"739545","mask":"+_ (_____) _-__-__"},{"code":"739546","mask":"+_ (_____) _-__-__"},{"code":"739549","mask":"+_ (_____) _-__-__"},{"code":"739562","mask":"+_ (_____) _-__-__"},{"code":"739563","mask":"+_ (_____) _-__-__"},{"code":"739565","mask":"+_ (_____) _-__-__"},{"code":"739566","mask":"+_ (_____) _-__-__"},{"code":"739567","mask":"+_ (_____) _-__-__"},{"code":"739568","mask":"+_ (_____) _-__-__"},{"code":"7401","mask":"+_ (___) ___-__-__"},{"code":"74012","mask":"+_ (____) __-__-__"},{"code":"740141","mask":"+_ (_____) _-__-__"},{"code":"740142","mask":"+_ (_____) _-__-__"},{"code":"740143","mask":"+_ (_____) _-__-__"},{"code":"740144","mask":"+_ (_____) _-__-__"},{"code":"740145","mask":"+_ (_____) _-__-__"},{"code":"740150","mask":"+_ (_____) _-__-__"},{"code":"740151","mask":"+_ (_____) _-__-__"},{"code":"740152","mask":"+_ (_____) _-__-__"},{"code":"740153","mask":"+_ (_____) _-__-__"},{"code":"740156","mask":"+_ (_____) _-__-__"},{"code":"740157","mask":"+_ (_____) _-__-__"},{"code":"740158","mask":"+_ (_____) _-__-__"},{"code":"740159","mask":"+_ (_____) _-__-__"},{"code":"740161","mask":"+_ (_____) _-__-__"},{"code":"740162","mask":"+_ (_____) _-__-__"},{"code":"740163","mask":"+_ (_____) _-__-__"},{"code":"740164","mask":"+_ (_____) _-__-__"},{"code":"7411","mask":"+_ (___) ___-__-__"},{"code":"74112","mask":"+_ (____) __-__-__"},{"code":"741131","mask":"+_ (_____) _-__-__"},{"code":"741132","mask":"+_ (_____) _-__-__"},{"code":"741133","mask":"+_ (_____) _-__-__"},{"code":"741134","mask":"+_ (_____) _-__-__"},{"code":"741135","mask":"+_ (_____) _-__-__"},{"code":"741136","mask":"+_ (_____) _-__-__"},{"code":"741137","mask":"+_ (_____) _-__-__"},{"code":"741138","mask":"+_ (_____) _-__-__"},{"code":"741141","mask":"+_ (_____) _-__-__"},{"code":"741142","mask":"+_ (_____) _-__-__"},{"code":"741143","mask":"+_ (_____) _-__-__"},{"code":"741144","mask":"+_ (_____) _-__-__"},{"code":"741145","mask":"+_ (_____) _-__-__"},{"code":"741147","mask":"+_ (_____) _-__-__"},{"code":"741151","mask":"+_ (_____) _-__-__"},{"code":"741152","mask":"+_ (_____) _-__-__"},{"code":"741153","mask":"+_ (_____) _-__-__"},{"code":"741162","mask":"+_ (_____) _-__-__"},{"code":"741163","mask":"+_ (_____) _-__-__"},{"code":"741167","mask":"+_ (_____) _-__-__"},{"code":"7413","mask":"+_ (___) ___-__-__"},{"code":"741342","mask":"+_ (_____) _-__-__"},{"code":"741344","mask":"+_ (_____) _-__-__"},{"code":"741345","mask":"+_ (_____) _-__-__"},{"code":"741346","mask":"+_ (_____) _-__-__"},{"code":"741347","mask":"+_ (_____) _-__-__"},{"code":"7415","mask":"+_ (___) ___-__-__"},{"code":"74152","mask":"+_ (____) __-__-__"},{"code":"741531","mask":"+_ (_____) _-__-__"},{"code":"741532","mask":"+_ (_____) _-__-__"},{"code":"741533","mask":"+_ (_____) _-__-__"},{"code":"741535","mask":"+_ (_____) _-__-__"},{"code":"741536","mask":"+_ (_____) _-__-__"},{"code":"741537","mask":"+_ (_____) _-__-__"},{"code":"741538","mask":"+_ (_____) _-__-__"},{"code":"741539","mask":"+_ (_____) _-__-__"},{"code":"741541","mask":"+_ (_____) _-__-__"},{"code":"741542","mask":"+_ (_____) _-__-__"},{"code":"741543","mask":"+_ (_____) _-__-__"},{"code":"741544","mask":"+_ (_____) _-__-__"},{"code":"741545","mask":"+_ (_____) _-__-__"},{"code":"741546","mask":"+_ (_____) _-__-__"},{"code":"7416","mask":"+_ (___) ___-__-__"},{"code":"74162","mask":"+_ (____) __-__-__"},{"code":"741636","mask":"+_ (_____) _-__-__"},{"code":"741639","mask":"+_ (_____) _-__-__"},{"code":"741641","mask":"+_ (_____) _-__-__"},{"code":"741642","mask":"+_ (_____) _-__-__"},{"code":"741643","mask":"+_ (_____) _-__-__"},{"code":"741644","mask":"+_ (_____) _-__-__"},{"code":"741647","mask":"+_ (_____) _-__-__"},{"code":"741649","mask":"+_ (_____) _-__-__"},{"code":"741651","mask":"+_ (_____) _-__-__"},{"code":"741654","mask":"+_ (_____) _-__-__"},{"code":"741658","mask":"+_ (_____) _-__-__"},{"code":"7421","mask":"+_ (___) ___-__-__"},{"code":"74212","mask":"+_ (____) __-__-__"},{"code":"742135","mask":"+_ (_____) _-__-__"},{"code":"742137","mask":"+_ (_____) _-__-__"},{"code":"742138","mask":"+_ (_____) _-__-__"},{"code":"742141","mask":"+_ (_____) _-__-__"},{"code":"742142","mask":"+_ (_____) _-__-__"},{"code":"742143","mask":"+_ (_____) _-__-__"},{"code":"742144","mask":"+_ (_____) _-__-__"},{"code":"742146","mask":"+_ (_____) _-__-__"},{"code":"742147","mask":"+_ (_____) _-__-__"},{"code":"742149","mask":"+_ (_____) _-__-__"},{"code":"742151","mask":"+_ (_____) _-__-__"},{"code":"742153","mask":"+_ (_____) _-__-__"},{"code":"742154","mask":"+_ (_____) _-__-__"},{"code":"742155","mask":"+_ (_____) _-__-__"},{"code":"742156","mask":"+_ (_____) _-__-__"},{"code":"7423","mask":"+_ (___) ___-__-__"},{"code":"742331","mask":"+_ (_____) _-__-__"},{"code":"742334","mask":"+_ (_____) _-__-__"},{"code":"742335","mask":"+_ (_____) _-__-__"},{"code":"742337","mask":"+_ (_____) _-__-__"},{"code":"742339","mask":"+_ (_____) _-__-__"},{"code":"74234","mask":"+_ (____) __-__-__"},{"code":"742344","mask":"+_ (_____) _-__-__"},{"code":"742345","mask":"+_ (_____) _-__-__"},{"code":"742346","mask":"+_ (_____) _-__-__"},{"code":"742347","mask":"+_ (_____) _-__-__"},{"code":"742349","mask":"+_ (_____) _-__-__"},{"code":"742351","mask":"+_ (_____) _-__-__"},{"code":"742352","mask":"+_ (_____) _-__-__"},{"code":"742354","mask":"+_ (_____) _-__-__"},{"code":"742355","mask":"+_ (_____) _-__-__"},{"code":"742356","mask":"+_ (_____) _-__-__"},{"code":"742357","mask":"+_ (_____) _-__-__"},{"code":"742361","mask":"+_ (_____) _-__-__"},{"code":"742362","mask":"+_ (_____) _-__-__"},{"code":"742365","mask":"+_ (_____) _-__-__"},{"code":"742371","mask":"+_ (_____) _-__-__"},{"code":"742372","mask":"+_ (_____) _-__-__"},{"code":"742373","mask":"+_ (_____) _-__-__"},{"code":"742374","mask":"+_ (_____) _-__-__"},{"code":"742375","mask":"+_ (_____) _-__-__"},{"code":"742376","mask":"+_ (_____) _-__-__"},{"code":"742377","mask":"+_ (_____) _-__-__"},{"code":"7424","mask":"+_ (___) ___-__-__"},{"code":"74242","mask":"+_ (____) __-__-__"},{"code":"742443","mask":"+_ (_____) _-__-__"},{"code":"7426","mask":"+_ (___) ___-__-__"},{"code":"742622","mask":"+_ (_____) _-__-__"},{"code":"7427","mask":"+_ (___) ___-__-__"},{"code":"742722","mask":"+_ (_____) _-__-__"},{"code":"7471","mask":"+_ (___) ___-__-__"},{"code":"74712","mask":"+_ (____) __-__-__"},{"code":"747131","mask":"+_ (_____) _-__-__"},{"code":"747132","mask":"+_ (_____) _-__-__"},{"code":"747133","mask":"+_ (_____) _-__-__"},{"code":"747134","mask":"+_ (_____) _-__-__"},{"code":"747135","mask":"+_ (_____) _-__-__"},{"code":"747136","mask":"+_ (_____) _-__-__"},{"code":"747137","mask":"+_ (_____) _-__-__"},{"code":"747140","mask":"+_ (_____) _-__-__"},{"code":"747141","mask":"+_ (_____) _-__-__"},{"code":"747142","mask":"+_ (_____) _-__-__"},{"code":"747143","mask":"+_ (_____) _-__-__"},{"code":"747144","mask":"+_ (_____) _-__-__"},{"code":"747145","mask":"+_ (_____) _-__-__"},{"code":"747146","mask":"+_ (_____) _-__-__"},{"code":"747147","mask":"+_ (_____) _-__-__"},{"code":"747148","mask":"+_ (_____) _-__-__"},{"code":"747149","mask":"+_ (_____) _-__-__"},{"code":"747150","mask":"+_ (_____) _-__-__"},{"code":"747151","mask":"+_ (_____) _-__-__"},{"code":"747152","mask":"+_ (_____) _-__-__"},{"code":"747153","mask":"+_ (_____) _-__-__"},{"code":"747154","mask":"+_ (_____) _-__-__"},{"code":"747155","mask":"+_ (_____) _-__-__"},{"code":"747156","mask":"+_ (_____) _-__-__"},{"code":"747157","mask":"+_ (_____) _-__-__"},{"code":"747158","mask":"+_ (_____) _-__-__"},{"code":"747159","mask":"+_ (_____) _-__-__"},{"code":"7472","mask":"+_ (___) ___-__-__"},{"code":"74722","mask":"+_ (____) __-__-__"},{"code":"747231","mask":"+_ (_____) _-__-__"},{"code":"747232","mask":"+_ (_____) _-__-__"},{"code":"747233","mask":"+_ (_____) _-__-__"},{"code":"747234","mask":"+_ (_____) _-__-__"},{"code":"747235","mask":"+_ (_____) _-__-__"},{"code":"747236","mask":"+_ (_____) _-__-__"},{"code":"747237","mask":"+_ (_____) _-__-__"},{"code":"747238","mask":"+_ (_____) _-__-__"},{"code":"747241","mask":"+_ (_____) _-__-__"},{"code":"747242","mask":"+_ (_____) _-__-__"},{"code":"747243","mask":"+_ (_____) _-__-__"},{"code":"747244","mask":"+_ (_____) _-__-__"},{"code":"747245","mask":"+_ (_____) _-__-__"},{"code":"747246","mask":"+_ (_____) _-__-__"},{"code":"747247","mask":"+_ (_____) _-__-__"},{"code":"747248","mask":"+_ (_____) _-__-__"},{"code":"74725","mask":"+_ (____) __-__-__"},{"code":"747261","mask":"+_ (_____) _-__-__"},{"code":"747262","mask":"+_ (_____) _-__-__"},{"code":"7473","mask":"+_ (___) ___-__-__"},{"code":"747340","mask":"+_ (_____) _-__-__"},{"code":"747341","mask":"+_ (_____) _-__-__"},{"code":"747342","mask":"+_ (_____) _-__-__"},{"code":"747343","mask":"+_ (_____) _-__-__"},{"code":"747344","mask":"+_ (_____) _-__-__"},{"code":"747345","mask":"+_ (_____) _-__-__"},{"code":"747346","mask":"+_ (_____) _-__-__"},{"code":"747347","mask":"+_ (_____) _-__-__"},{"code":"747348","mask":"+_ (_____) _-__-__"},{"code":"747350","mask":"+_ (_____) _-__-__"},{"code":"747352","mask":"+_ (_____) _-__-__"},{"code":"747353","mask":"+_ (_____) _-__-__"},{"code":"747354","mask":"+_ (_____) _-__-__"},{"code":"747355","mask":"+_ (_____) _-__-__"},{"code":"747356","mask":"+_ (_____) _-__-__"},{"code":"747357","mask":"+_ (_____) _-__-__"},{"code":"747361","mask":"+_ (_____) _-__-__"},{"code":"747362","mask":"+_ (_____) _-__-__"},{"code":"747363","mask":"+_ (_____) _-__-__"},{"code":"747364","mask":"+_ (_____) _-__-__"},{"code":"747365","mask":"+_ (_____) _-__-__"},{"code":"747366","mask":"+_ (_____) _-__-__"},{"code":"747367","mask":"+_ (_____) _-__-__"},{"code":"747370","mask":"+_ (_____) _-__-__"},{"code":"747371","mask":"+_ (_____) _-__-__"},{"code":"747372","mask":"+_ (_____) _-__-__"},{"code":"747374","mask":"+_ (_____) _-__-__"},{"code":"747375","mask":"+_ (_____) _-__-__"},{"code":"747376","mask":"+_ (_____) _-__-__"},{"code":"747391","mask":"+_ (_____) _-__-__"},{"code":"747394","mask":"+_ (_____) _-__-__"},{"code":"747395","mask":"+_ (_____) _-__-__"},{"code":"747396","mask":"+_ (_____) _-__-__"},{"code":"7474","mask":"+_ (___) ___-__-__"},{"code":"74742","mask":"+_ (____) __-__-__"},{"code":"747461","mask":"+_ (_____) _-__-__"},{"code":"747462","mask":"+_ (_____) _-__-__"},{"code":"747463","mask":"+_ (_____) _-__-__"},{"code":"747464","mask":"+_ (_____) _-__-__"},{"code":"747465","mask":"+_ (_____) _-__-__"},{"code":"747466","mask":"+_ (_____) _-__-__"},{"code":"747467","mask":"+_ (_____) _-__-__"},{"code":"747468","mask":"+_ (_____) _-__-__"},{"code":"747469","mask":"+_ (_____) _-__-__"},{"code":"747471","mask":"+_ (_____) _-__-__"},{"code":"747472","mask":"+_ (_____) _-__-__"},{"code":"747473","mask":"+_ (_____) _-__-__"},{"code":"747474","mask":"+_ (_____) _-__-__"},{"code":"747475","mask":"+_ (_____) _-__-__"},{"code":"747476","mask":"+_ (_____) _-__-__"},{"code":"747477","mask":"+_ (_____) _-__-__"},{"code":"747478","mask":"+_ (_____) _-__-__"},{"code":"7475","mask":"+_ (___) ___-__-__"},{"code":"74752","mask":"+_ (____) __-__-__"},{"code":"747531","mask":"+_ (_____) _-__-__"},{"code":"747532","mask":"+_ (_____) _-__-__"},{"code":"747533","mask":"+_ (_____) _-__-__"},{"code":"747534","mask":"+_ (_____) _-__-__"},{"code":"747535","mask":"+_ (_____) _-__-__"},{"code":"747536","mask":"+_ (_____) _-__-__"},{"code":"747537","mask":"+_ (_____) _-__-__"},{"code":"747541","mask":"+_ (_____) _-__-__"},{"code":"747542","mask":"+_ (_____) _-__-__"},{"code":"747543","mask":"+_ (_____) _-__-__"},{"code":"747544","mask":"+_ (_____) _-__-__"},{"code":"747545","mask":"+_ (_____) _-__-__"},{"code":"747546","mask":"+_ (_____) _-__-__"},{"code":"747548","mask":"+_ (_____) _-__-__"},{"code":"747551","mask":"+_ (_____) _-__-__"},{"code":"747552","mask":"+_ (_____) _-__-__"},{"code":"747553","mask":"+_ (_____) _-__-__"},{"code":"747554","mask":"+_ (_____) _-__-__"},{"code":"747555","mask":"+_ (_____) _-__-__"},{"code":"747556","mask":"+_ (_____) _-__-__"},{"code":"747557","mask":"+_ (_____) _-__-__"},{"code":"747558","mask":"+_ (_____) _-__-__"},{"code":"747559","mask":"+_ (_____) _-__-__"},{"code":"7481","mask":"+_ (___) ___-__-__"},{"code":"74812","mask":"+_ (____) __-__-__"},{"code":"748130","mask":"+_ (_____) _-__-__"},{"code":"748131","mask":"+_ (_____) _-__-__"},{"code":"748132","mask":"+_ (_____) _-__-__"},{"code":"748133","mask":"+_ (_____) _-__-__"},{"code":"748134","mask":"+_ (_____) _-__-__"},{"code":"748135","mask":"+_ (_____) _-__-__"},{"code":"748136","mask":"+_ (_____) _-__-__"},{"code":"748137","mask":"+_ (_____) _-__-__"},{"code":"748138","mask":"+_ (_____) _-__-__"},{"code":"748139","mask":"+_ (_____) _-__-__"},{"code":"748140","mask":"+_ (_____) _-__-__"},{"code":"748141","mask":"+_ (_____) _-__-__"},{"code":"748142","mask":"+_ (_____) _-__-__"},{"code":"748143","mask":"+_ (_____) _-__-__"},{"code":"748144","mask":"+_ (_____) _-__-__"},{"code":"748145","mask":"+_ (_____) _-__-__"},{"code":"748146","mask":"+_ (_____) _-__-__"},{"code":"748147","mask":"+_ (_____) _-__-__"},{"code":"748148","mask":"+_ (_____) _-__-__"},{"code":"748149","mask":"+_ (_____) _-__-__"},{"code":"748153","mask":"+_ (_____) _-__-__"},{"code":"748155","mask":"+_ (_____) _-__-__"},{"code":"748165","mask":"+_ (_____) _-__-__"},{"code":"748166","mask":"+_ (_____) _-__-__"},{"code":"748167","mask":"+_ (_____) _-__-__"},{"code":"7482","mask":"+_ (___) ___-__-__"},{"code":"748230","mask":"+_ (_____) _-__-__"},{"code":"748231","mask":"+_ (_____) _-__-__"},{"code":"748233","mask":"+_ (_____) _-__-__"},{"code":"748234","mask":"+_ (_____) _-__-__"},{"code":"748235","mask":"+_ (_____) _-__-__"},{"code":"748236","mask":"+_ (_____) _-__-__"},{"code":"748237","mask":"+_ (_____) _-__-__"},{"code":"748238","mask":"+_ (_____) _-__-__"},{"code":"748239","mask":"+_ (_____) _-__-__"},{"code":"748242","mask":"+_ (_____) _-__-__"},{"code":"748244","mask":"+_ (_____) _-__-__"},{"code":"748246","mask":"+_ (_____) _-__-__"},{"code":"748249","mask":"+_ (_____) _-__-__"},{"code":"748250","mask":"+_ (_____) _-__-__"},{"code":"748251","mask":"+_ (_____) _-__-__"},{"code":"748253","mask":"+_ (_____) _-__-__"},{"code":"748255","mask":"+_ (_____) _-__-__"},{"code":"748257","mask":"+_ (_____) _-__-__"},{"code":"748258","mask":"+_ (_____) _-__-__"},{"code":"748261","mask":"+_ (_____) _-__-__"},{"code":"748262","mask":"+_ (_____) _-__-__"},{"code":"748263","mask":"+_ (_____) _-__-__"},{"code":"748265","mask":"+_ (_____) _-__-__"},{"code":"748266","mask":"+_ (_____) _-__-__"},{"code":"748267","mask":"+_ (_____) _-__-__"},{"code":"748268","mask":"+_ (_____) _-__-__"},{"code":"748271","mask":"+_ (_____) _-__-__"},{"code":"748272","mask":"+_ (_____) _-__-__"},{"code":"7483","mask":"+_ (___) ___-__-__"},{"code":"748330","mask":"+_ (_____) _-__-__"},{"code":"748331","mask":"+_ (_____) _-__-__"},{"code":"748332","mask":"+_ (_____) _-__-__"},{"code":"748333","mask":"+_ (_____) _-__-__"},{"code":"748334","mask":"+_ (_____) _-__-__"},{"code":"748335","mask":"+_ (_____) _-__-__"},{"code":"748336","mask":"+_ (_____) _-__-__"},{"code":"748338","mask":"+_ (_____) _-__-__"},{"code":"748339","mask":"+_ (_____) _-__-__"},{"code":"748340","mask":"+_ (_____) _-__-__"},{"code":"748341","mask":"+_ (_____) _-__-__"},{"code":"748342","mask":"+_ (_____) _-__-__"},{"code":"748343","mask":"+_ (_____) _-__-__"},{"code":"748344","mask":"+_ (_____) _-__-__"},{"code":"748345","mask":"+_ (_____) _-__-__"},{"code":"748346","mask":"+_ (_____) _-__-__"},{"code":"748347","mask":"+_ (_____) _-__-__"},{"code":"748348","mask":"+_ (_____) _-__-__"},{"code":"748349","mask":"+_ (_____) _-__-__"},{"code":"748351","mask":"+_ (_____) _-__-__"},{"code":"748352","mask":"+_ (_____) _-__-__"},{"code":"748353","mask":"+_ (_____) _-__-__"},{"code":"748354","mask":"+_ (_____) _-__-__"},{"code":"748355","mask":"+_ (_____) _-__-__"},{"code":"748356","mask":"+_ (_____) _-__-__"},{"code":"748358","mask":"+_ (_____) _-__-__"},{"code":"7484","mask":"+_ (___) ___-__-__"},{"code":"74842","mask":"+_ (____) __-__-__"},{"code":"748431","mask":"+_ (_____) _-__-__"},{"code":"748432","mask":"+_ (_____) _-__-__"},{"code":"748433","mask":"+_ (_____) _-__-__"},{"code":"748434","mask":"+_ (_____) _-__-__"},{"code":"748435","mask":"+_ (_____) _-__-__"},{"code":"748436","mask":"+_ (_____) _-__-__"},{"code":"748437","mask":"+_ (_____) _-__-__"},{"code":"748439","mask":"+_ (_____) _-__-__"},{"code":"748441","mask":"+_ (_____) _-__-__"},{"code":"748442","mask":"+_ (_____) _-__-__"},{"code":"748443","mask":"+_ (_____) _-__-__"},{"code":"748444","mask":"+_ (_____) _-__-__"},{"code":"748445","mask":"+_ (_____) _-__-__"},{"code":"748446","mask":"+_ (_____) _-__-__"},{"code":"748447","mask":"+_ (_____) _-__-__"},{"code":"748448","mask":"+_ (_____) _-__-__"},{"code":"748451","mask":"+_ (_____) _-__-__"},{"code":"748452","mask":"+_ (_____) _-__-__"},{"code":"748453","mask":"+_ (_____) _-__-__"},{"code":"748455","mask":"+_ (_____) _-__-__"},{"code":"748456","mask":"+_ (_____) _-__-__"},{"code":"7485","mask":"+_ (___) ___-__-__"},{"code":"74852","mask":"+_ (____) __-__-__"},{"code":"748531","mask":"+_ (_____) _-__-__"},{"code":"748532","mask":"+_ (_____) _-__-__"},{"code":"748533","mask":"+_ (_____) _-__-__"},{"code":"748534","mask":"+_ (_____) _-__-__"},{"code":"748535","mask":"+_ (_____) _-__-__"},{"code":"748536","mask":"+_ (_____) _-__-__"},{"code":"748538","mask":"+_ (_____) _-__-__"},{"code":"748539","mask":"+_ (_____) _-__-__"},{"code":"748542","mask":"+_ (_____) _-__-__"},{"code":"748543","mask":"+_ (_____) _-__-__"},{"code":"748544","mask":"+_ (_____) _-__-__"},{"code":"748545","mask":"+_ (_____) _-__-__"},{"code":"748546","mask":"+_ (_____) _-__-__"},{"code":"748547","mask":"+_ (_____) _-__-__"},{"code":"748549","mask":"+_ (_____) _-__-__"},{"code":"74855","mask":"+_ (____) __-__-__"},{"code":"7486","mask":"+_ (___) ___-__-__"},{"code":"74862","mask":"+_ (____) __-__-__"},{"code":"748640","mask":"+_ (_____) _-__-__"},{"code":"748643","mask":"+_ (_____) _-__-__"},{"code":"748645","mask":"+_ (_____) _-__-__"},{"code":"748646","mask":"+_ (_____) _-__-__"},{"code":"748647","mask":"+_ (_____) _-__-__"},{"code":"748648","mask":"+_ (_____) _-__-__"},{"code":"748649","mask":"+_ (_____) _-__-__"},{"code":"748662","mask":"+_ (_____) _-__-__"},{"code":"748664","mask":"+_ (_____) _-__-__"},{"code":"748666","mask":"+_ (_____) _-__-__"},{"code":"748674","mask":"+_ (_____) _-__-__"},{"code":"748675","mask":"+_ (_____) _-__-__"},{"code":"748676","mask":"+_ (_____) _-__-__"},{"code":"748677","mask":"+_ (_____) _-__-__"},{"code":"748679","mask":"+_ (_____) _-__-__"},{"code":"7487","mask":"+_ (___) ___-__-__"},{"code":"74872","mask":"+_ (____) __-__-__"},{"code":"748731","mask":"+_ (_____) _-__-__"},{"code":"748732","mask":"+_ (_____) _-__-__"},{"code":"748733","mask":"+_ (_____) _-__-__"},{"code":"748734","mask":"+_ (_____) _-__-__"},{"code":"748735","mask":"+_ (_____) _-__-__"},{"code":"748736","mask":"+_ (_____) _-__-__"},{"code":"748741","mask":"+_ (_____) _-__-__"},{"code":"748742","mask":"+_ (_____) _-__-__"},{"code":"748743","mask":"+_ (_____) _-__-__"},{"code":"748744","mask":"+_ (_____) _-__-__"},{"code":"748745","mask":"+_ (_____) _-__-__"},{"code":"748746","mask":"+_ (_____) _-__-__"},{"code":"748751","mask":"+_ (_____) _-__-__"},{"code":"748752","mask":"+_ (_____) _-__-__"},{"code":"748753","mask":"+_ (_____) _-__-__"},{"code":"748754","mask":"+_ (_____) _-__-__"},{"code":"748755","mask":"+_ (_____) _-__-__"},{"code":"748756","mask":"+_ (_____) _-__-__"},{"code":"748761","mask":"+_ (_____) _-__-__"},{"code":"748762","mask":"+_ (_____) _-__-__"},{"code":"748763","mask":"+_ (_____) _-__-__"},{"code":"748766","mask":"+_ (_____) _-__-__"},{"code":"748767","mask":"+_ (_____) _-__-__"},{"code":"748768","mask":"+_ (_____) _-__-__"},{"code":"7491","mask":"+_ (___) ___-__-__"},{"code":"74912","mask":"+_ (____) __-__-__"},{"code":"749130","mask":"+_ (_____) _-__-__"},{"code":"749131","mask":"+_ (_____) _-__-__"},{"code":"749132","mask":"+_ (_____) _-__-__"},{"code":"749133","mask":"+_ (_____) _-__-__"},{"code":"749135","mask":"+_ (_____) _-__-__"},{"code":"749136","mask":"+_ (_____) _-__-__"},{"code":"749137","mask":"+_ (_____) _-__-__"},{"code":"749138","mask":"+_ (_____) _-__-__"},{"code":"749139","mask":"+_ (_____) _-__-__"},{"code":"749141","mask":"+_ (_____) _-__-__"},{"code":"749142","mask":"+_ (_____) _-__-__"},{"code":"749143","mask":"+_ (_____) _-__-__"},{"code":"749144","mask":"+_ (_____) _-__-__"},{"code":"749145","mask":"+_ (_____) _-__-__"},{"code":"749146","mask":"+_ (_____) _-__-__"},{"code":"749147","mask":"+_ (_____) _-__-__"},{"code":"749151","mask":"+_ (_____) _-__-__"},{"code":"749152","mask":"+_ (_____) _-__-__"},{"code":"749154","mask":"+_ (_____) _-__-__"},{"code":"749155","mask":"+_ (_____) _-__-__"},{"code":"749156","mask":"+_ (_____) _-__-__"},{"code":"749157","mask":"+_ (_____) _-__-__"},{"code":"749158","mask":"+_ (_____) _-__-__"},{"code":"7492","mask":"+_ (___) ___-__-__"},{"code":"74922","mask":"+_ (____) __-__-__"},{"code":"749231","mask":"+_ (_____) _-__-__"},{"code":"749232","mask":"+_ (_____) _-__-__"},{"code":"749234","mask":"+_ (_____) _-__-__"},{"code":"749235","mask":"+_ (_____) _-__-__"},{"code":"749236","mask":"+_ (_____) _-__-__"},{"code":"749237","mask":"+_ (_____) _-__-__"},{"code":"749238","mask":"+_ (_____) _-__-__"},{"code":"749241","mask":"+_ (_____) _-__-__"},{"code":"749242","mask":"+_ (_____) _-__-__"},{"code":"749244","mask":"+_ (_____) _-__-__"},{"code":"749245","mask":"+_ (_____) _-__-__"},{"code":"749246","mask":"+_ (_____) _-__-__"},{"code":"749247","mask":"+_ (_____) _-__-__"},{"code":"749248","mask":"+_ (_____) _-__-__"},{"code":"749254","mask":"+_ (_____) _-__-__"},{"code":"7493","mask":"+_ (___) ___-__-__"},{"code":"74932","mask":"+_ (____) __-__-__"},{"code":"749331","mask":"+_ (_____) _-__-__"},{"code":"749334","mask":"+_ (_____) _-__-__"},{"code":"749336","mask":"+_ (_____) _-__-__"},{"code":"749337","mask":"+_ (_____) _-__-__"},{"code":"749339","mask":"+_ (_____) _-__-__"},{"code":"749341","mask":"+_ (_____) _-__-__"},{"code":"749343","mask":"+_ (_____) _-__-__"},{"code":"749345","mask":"+_ (_____) _-__-__"},{"code":"749346","mask":"+_ (_____) _-__-__"},{"code":"749347","mask":"+_ (_____) _-__-__"},{"code":"749349","mask":"+_ (_____) _-__-__"},{"code":"749351","mask":"+_ (_____) _-__-__"},{"code":"749352","mask":"+_ (_____) _-__-__"},{"code":"749353","mask":"+_ (_____) _-__-__"},{"code":"749354","mask":"+_ (_____) _-__-__"},{"code":"749355","mask":"+_ (_____) _-__-__"},{"code":"749356","mask":"+_ (_____) _-__-__"},{"code":"749357","mask":"+_ (_____) _-__-__"},{"code":"7494","mask":"+_ (___) ___-__-__"},{"code":"74942","mask":"+_ (____) __-__-__"},{"code":"749430","mask":"+_ (_____) _-__-__"},{"code":"749431","mask":"+_ (_____) _-__-__"},{"code":"749432","mask":"+_ (_____) _-__-__"},{"code":"749433","mask":"+_ (_____) _-__-__"},{"code":"749434","mask":"+_ (_____) _-__-__"},{"code":"749435","mask":"+_ (_____) _-__-__"},{"code":"749436","mask":"+_ (_____) _-__-__"},{"code":"749437","mask":"+_ (_____) _-__-__"},{"code":"749438","mask":"+_ (_____) _-__-__"},{"code":"749439","mask":"+_ (_____) _-__-__"},{"code":"749440","mask":"+_ (_____) _-__-__"},{"code":"749441","mask":"+_ (_____) _-__-__"},{"code":"749442","mask":"+_ (_____) _-__-__"},{"code":"749443","mask":"+_ (_____) _-__-__"},{"code":"749444","mask":"+_ (_____) _-__-__"},{"code":"749445","mask":"+_ (_____) _-__-__"},{"code":"749446","mask":"+_ (_____) _-__-__"},{"code":"749447","mask":"+_ (_____) _-__-__"},{"code":"749448","mask":"+_ (_____) _-__-__"},{"code":"749449","mask":"+_ (_____) _-__-__"},{"code":"749450","mask":"+_ (_____) _-__-__"},{"code":"749451","mask":"+_ (_____) _-__-__"},{"code":"749452","mask":"+_ (_____) _-__-__"},{"code":"749453","mask":"+_ (_____) _-__-__"},{"code":"7495","mask":"+_ (___) ___-__-__"},{"code":"7496","mask":"+_ (___) ___-__-__"},{"code":"749620","mask":"+_ (___) ___-__-__"},{"code":"749621","mask":"+_ (___) ___-__-__"},{"code":"749622","mask":"+_ (___) ___-__-__"},{"code":"749624","mask":"+_ (___) ___-__-__"},{"code":"749626","mask":"+_ (___) ___-__-__"},{"code":"749627","mask":"+_ (___) ___-__-__"},{"code":"749628","mask":"+_ (___) ___-__-__"},{"code":"749631","mask":"+_ (___) ___-__-__"},{"code":"749634","mask":"+_ (___) ___-__-__"},{"code":"749636","mask":"+_ (___) ___-__-__"},{"code":"749637","mask":"+_ (___) ___-__-__"},{"code":"749638","mask":"+_ (___) ___-__-__"},{"code":"749640","mask":"+_ (___) ___-__-__"},{"code":"749643","mask":"+_ (___) ___-__-__"},{"code":"749644","mask":"+_ (___) ___-__-__"},{"code":"749645","mask":"+_ (___) ___-__-__"},{"code":"749646","mask":"+_ (___) ___-__-__"},{"code":"749651","mask":"+_ (___) ___-__-__"},{"code":"749652","mask":"+_ (___) ___-__-__"},{"code":"749653","mask":"+_ (___) ___-__-__"},{"code":"749654","mask":"+_ (___) ___-__-__"},{"code":"749656","mask":"+_ (___) ___-__-__"},{"code":"749657","mask":"+_ (___) ___-__-__"},{"code":"749663","mask":"+_ (___) ___-__-__"},{"code":"749664","mask":"+_ (___) ___-__-__"},{"code":"749666","mask":"+_ (___) ___-__-__"},{"code":"749667","mask":"+_ (___) ___-__-__"},{"code":"749670","mask":"+_ (___) ___-__-__"},{"code":"749672","mask":"+_ (___) ___-__-__"},{"code":"749679","mask":"+_ (___) ___-__-__"},{"code":"7498","mask":"+_ (___) ___-__-__"},{"code":"7499","mask":"+_ (___) ___-__-__"},{"code":"7811","mask":"+_ (___) ___-__-__"},{"code":"78112","mask":"+_ (____) __-__-__"},{"code":"781131","mask":"+_ (_____) _-__-__"},{"code":"781132","mask":"+_ (_____) _-__-__"},{"code":"781133","mask":"+_ (_____) _-__-__"},{"code":"781134","mask":"+_ (_____) _-__-__"},{"code":"781135","mask":"+_ (_____) _-__-__"},{"code":"781136","mask":"+_ (_____) _-__-__"},{"code":"781137","mask":"+_ (_____) _-__-__"},{"code":"781138","mask":"+_ (_____) _-__-__"},{"code":"781139","mask":"+_ (_____) _-__-__"},{"code":"781140","mask":"+_ (_____) _-__-__"},{"code":"781141","mask":"+_ (_____) _-__-__"},{"code":"781142","mask":"+_ (_____) _-__-__"},{"code":"781143","mask":"+_ (_____) _-__-__"},{"code":"781144","mask":"+_ (_____) _-__-__"},{"code":"781145","mask":"+_ (_____) _-__-__"},{"code":"781146","mask":"+_ (_____) _-__-__"},{"code":"781147","mask":"+_ (_____) _-__-__"},{"code":"781148","mask":"+_ (_____) _-__-__"},{"code":"781149","mask":"+_ (_____) _-__-__"},{"code":"781150","mask":"+_ (_____) _-__-__"},{"code":"781151","mask":"+_ (_____) _-__-__"},{"code":"781152","mask":"+_ (_____) _-__-__"},{"code":"781153","mask":"+_ (_____) _-__-__"},{"code":"7812","mask":"+_ (___) ___-__-__"},{"code":"7813","mask":"+_ (___) ___-__-__"},{"code":"7814","mask":"+_ (___) ___-__-__"},{"code":"78142","mask":"+_ (____) __-__-__"},{"code":"781430","mask":"+_ (_____) _-__-__"},{"code":"781431","mask":"+_ (_____) _-__-__"},{"code":"781433","mask":"+_ (_____) _-__-__"},{"code":"781434","mask":"+_ (_____) _-__-__"},{"code":"781436","mask":"+_ (_____) _-__-__"},{"code":"781437","mask":"+_ (_____) _-__-__"},{"code":"781439","mask":"+_ (_____) _-__-__"},{"code":"781450","mask":"+_ (_____) _-__-__"},{"code":"781451","mask":"+_ (_____) _-__-__"},{"code":"781452","mask":"+_ (_____) _-__-__"},{"code":"781454","mask":"+_ (_____) _-__-__"},{"code":"781455","mask":"+_ (_____) _-__-__"},{"code":"781456","mask":"+_ (_____) _-__-__"},{"code":"781457","mask":"+_ (_____) _-__-__"},{"code":"781458","mask":"+_ (_____) _-__-__"},{"code":"781459","mask":"+_ (_____) _-__-__"},{"code":"7815","mask":"+_ (___) ___-__-__"},{"code":"78152","mask":"+_ (____) __-__-__"},{"code":"781530","mask":"+_ (_____) _-__-__"},{"code":"781531","mask":"+_ (_____) _-__-__"},{"code":"781532","mask":"+_ (_____) _-__-__"},{"code":"781533","mask":"+_ (_____) _-__-__"},{"code":"781535","mask":"+_ (_____) _-__-__"},{"code":"781536","mask":"+_ (_____) _-__-__"},{"code":"781537","mask":"+_ (_____) _-__-__"},{"code":"781538","mask":"+_ (_____) _-__-__"},{"code":"781551","mask":"+_ (_____) _-__-__"},{"code":"781552","mask":"+_ (_____) _-__-__"},{"code":"781553","mask":"+_ (_____) _-__-__"},{"code":"781554","mask":"+_ (_____) _-__-__"},{"code":"781555","mask":"+_ (_____) _-__-__"},{"code":"781556","mask":"+_ (_____) _-__-__"},{"code":"781559","mask":"+_ (_____) _-__-__"},{"code":"7816","mask":"+_ (___) ___-__-__"},{"code":"781650","mask":"+_ (_____) _-__-__"},{"code":"781651","mask":"+_ (_____) _-__-__"},{"code":"781652","mask":"+_ (_____) _-__-__"},{"code":"781653","mask":"+_ (_____) _-__-__"},{"code":"781654","mask":"+_ (_____) _-__-__"},{"code":"781655","mask":"+_ (_____) _-__-__"},{"code":"781656","mask":"+_ (_____) _-__-__"},{"code":"781657","mask":"+_ (_____) _-__-__"},{"code":"781658","mask":"+_ (_____) _-__-__"},{"code":"781659","mask":"+_ (_____) _-__-__"},{"code":"781660","mask":"+_ (_____) _-__-__"},{"code":"781661","mask":"+_ (_____) _-__-__"},{"code":"781662","mask":"+_ (_____) _-__-__"},{"code":"781663","mask":"+_ (_____) _-__-__"},{"code":"781664","mask":"+_ (_____) _-__-__"},{"code":"781665","mask":"+_ (_____) _-__-__"},{"code":"781666","mask":"+_ (_____) _-__-__"},{"code":"781667","mask":"+_ (_____) _-__-__"},{"code":"781668","mask":"+_ (_____) _-__-__"},{"code":"781669","mask":"+_ (_____) _-__-__"},{"code":"7817","mask":"+_ (___) ___-__-__"},{"code":"78172","mask":"+_ (____) __-__-__"},{"code":"781732","mask":"+_ (_____) _-__-__"},{"code":"781733","mask":"+_ (_____) _-__-__"},{"code":"781737","mask":"+_ (_____) _-__-__"},{"code":"781738","mask":"+_ (_____) _-__-__"},{"code":"781739","mask":"+_ (_____) _-__-__"},{"code":"781740","mask":"+_ (_____) _-__-__"},{"code":"781741","mask":"+_ (_____) _-__-__"},{"code":"781742","mask":"+_ (_____) _-__-__"},{"code":"781743","mask":"+_ (_____) _-__-__"},{"code":"781744","mask":"+_ (_____) _-__-__"},{"code":"781745","mask":"+_ (_____) _-__-__"},{"code":"781746","mask":"+_ (_____) _-__-__"},{"code":"781747","mask":"+_ (_____) _-__-__"},{"code":"781748","mask":"+_ (_____) _-__-__"},{"code":"781749","mask":"+_ (_____) _-__-__"},{"code":"781751","mask":"+_ (_____) _-__-__"},{"code":"781752","mask":"+_ (_____) _-__-__"},{"code":"781753","mask":"+_ (_____) _-__-__"},{"code":"781754","mask":"+_ (_____) _-__-__"},{"code":"781755","mask":"+_ (_____) _-__-__"},{"code":"781756","mask":"+_ (_____) _-__-__"},{"code":"781757","mask":"+_ (_____) _-__-__"},{"code":"781758","mask":"+_ (_____) _-__-__"},{"code":"781759","mask":"+_ (_____) _-__-__"},{"code":"7818","mask":"+_ (___) ___-__-__"},{"code":"781830","mask":"+_ (_____) _-__-__"},{"code":"781831","mask":"+_ (_____) _-__-__"},{"code":"781832","mask":"+_ (_____) _-__-__"},{"code":"781833","mask":"+_ (_____) _-__-__"},{"code":"781834","mask":"+_ (_____) _-__-__"},{"code":"781836","mask":"+_ (_____) _-__-__"},{"code":"781837","mask":"+_ (_____) _-__-__"},{"code":"781838","mask":"+_ (_____) _-__-__"},{"code":"781839","mask":"+_ (_____) _-__-__"},{"code":"781840","mask":"+_ (_____) _-__-__"},{"code":"781841","mask":"+_ (_____) _-__-__"},{"code":"781842","mask":"+_ (_____) _-__-__"},{"code":"781843","mask":"+_ (_____) _-__-__"},{"code":"781848","mask":"+_ (_____) _-__-__"},{"code":"781850","mask":"+_ (_____) _-__-__"},{"code":"781851","mask":"+_ (_____) _-__-__"},{"code":"781852","mask":"+_ (_____) _-__-__"},{"code":"781853","mask":"+_ (_____) _-__-__"},{"code":"781854","mask":"+_ (_____) _-__-__"},{"code":"781855","mask":"+_ (_____) _-__-__"},{"code":"781856","mask":"+_ (_____) _-__-__"},{"code":"781858","mask":"+_ (_____) _-__-__"},{"code":"781859","mask":"+_ (_____) _-__-__"},{"code":"7820","mask":"+_ (___) ___-__-__"},{"code":"78202","mask":"+_ (____) __-__-__"},{"code":"7821","mask":"+_ (___) ___-__-__"},{"code":"78212","mask":"+_ (____) __-__-__"},{"code":"782130","mask":"+_ (_____) _-__-__"},{"code":"782131","mask":"+_ (_____) _-__-__"},{"code":"782132","mask":"+_ (_____) _-__-__"},{"code":"782133","mask":"+_ (_____) _-__-__"},{"code":"782134","mask":"+_ (_____) _-__-__"},{"code":"782135","mask":"+_ (_____) _-__-__"},{"code":"782136","mask":"+_ (_____) _-__-__"},{"code":"782137","mask":"+_ (_____) _-__-__"},{"code":"782138","mask":"+_ (_____) _-__-__"},{"code":"782139","mask":"+_ (_____) _-__-__"},{"code":"782140","mask":"+_ (_____) _-__-__"},{"code":"782141","mask":"+_ (_____) _-__-__"},{"code":"782142","mask":"+_ (_____) _-__-__"},{"code":"782144","mask":"+_ (_____) _-__-__"},{"code":"782145","mask":"+_ (_____) _-__-__"},{"code":"782146","mask":"+_ (_____) _-__-__"},{"code":"782149","mask":"+_ (_____) _-__-__"},{"code":"782151","mask":"+_ (_____) _-__-__"},{"code":"7831","mask":"+_ (___) ___-__-__"},{"code":"78313","mask":"+_ (____) __-__-__"},{"code":"783130","mask":"+_ (_____) _-__-__"},{"code":"783138","mask":"+_ (_____) _-__-__"},{"code":"783144","mask":"+_ (_____) _-__-__"},{"code":"783145","mask":"+_ (_____) _-__-__"},{"code":"783147","mask":"+_ (_____) _-__-__"},{"code":"783148","mask":"+_ (_____) _-__-__"},{"code":"783149","mask":"+_ (_____) _-__-__"},{"code":"783150","mask":"+_ (_____) _-__-__"},{"code":"783152","mask":"+_ (_____) _-__-__"},{"code":"783153","mask":"+_ (_____) _-__-__"},{"code":"783154","mask":"+_ (_____) _-__-__"},{"code":"783155","mask":"+_ (_____) _-__-__"},{"code":"783156","mask":"+_ (_____) _-__-__"},{"code":"783157","mask":"+_ (_____) _-__-__"},{"code":"783158","mask":"+_ (_____) _-__-__"},{"code":"783159","mask":"+_ (_____) _-__-__"},{"code":"783160","mask":"+_ (_____) _-__-__"},{"code":"783161","mask":"+_ (_____) _-__-__"},{"code":"783162","mask":"+_ (_____) _-__-__"},{"code":"783163","mask":"+_ (_____) _-__-__"},{"code":"783164","mask":"+_ (_____) _-__-__"},{"code":"783165","mask":"+_ (_____) _-__-__"},{"code":"783166","mask":"+_ (_____) _-__-__"},{"code":"783167","mask":"+_ (_____) _-__-__"},{"code":"783168","mask":"+_ (_____) _-__-__"},{"code":"783169","mask":"+_ (_____) _-__-__"},{"code":"783170","mask":"+_ (_____) _-__-__"},{"code":"783171","mask":"+_ (_____) _-__-__"},{"code":"783172","mask":"+_ (_____) _-__-__"},{"code":"783173","mask":"+_ (_____) _-__-__"},{"code":"783174","mask":"+_ (_____) _-__-__"},{"code":"783175","mask":"+_ (_____) _-__-__"},{"code":"783176","mask":"+_ (_____) _-__-__"},{"code":"783177","mask":"+_ (_____) _-__-__"},{"code":"783178","mask":"+_ (_____) _-__-__"},{"code":"783179","mask":"+_ (_____) _-__-__"},{"code":"783191","mask":"+_ (_____) _-__-__"},{"code":"783192","mask":"+_ (_____) _-__-__"},{"code":"783193","mask":"+_ (_____) _-__-__"},{"code":"783194","mask":"+_ (_____) _-__-__"},{"code":"783195","mask":"+_ (_____) _-__-__"},{"code":"783196","mask":"+_ (_____) _-__-__"},{"code":"783197","mask":"+_ (_____) _-__-__"},{"code":"7833","mask":"+_ (___) ___-__-__"},{"code":"78332","mask":"+_ (____) __-__-__"},{"code":"783330","mask":"+_ (_____) _-__-__"},{"code":"783332","mask":"+_ (_____) _-__-__"},{"code":"783333","mask":"+_ (_____) _-__-__"},{"code":"783334","mask":"+_ (_____) _-__-__"},{"code":"783335","mask":"+_ (_____) _-__-__"},{"code":"783336","mask":"+_ (_____) _-__-__"},{"code":"783337","mask":"+_ (_____) _-__-__"},{"code":"783338","mask":"+_ (_____) _-__-__"},{"code":"783339","mask":"+_ (_____) _-__-__"},{"code":"783340","mask":"+_ (_____) _-__-__"},{"code":"783341","mask":"+_ (_____) _-__-__"},{"code":"783342","mask":"+_ (_____) _-__-__"},{"code":"783343","mask":"+_ (_____) _-__-__"},{"code":"783344","mask":"+_ (_____) _-__-__"},{"code":"783345","mask":"+_ (_____) _-__-__"},{"code":"783346","mask":"+_ (_____) _-__-__"},{"code":"783347","mask":"+_ (_____) _-__-__"},{"code":"783348","mask":"+_ (_____) _-__-__"},{"code":"783349","mask":"+_ (_____) _-__-__"},{"code":"783350","mask":"+_ (_____) _-__-__"},{"code":"783351","mask":"+_ (_____) _-__-__"},{"code":"783352","mask":"+_ (_____) _-__-__"},{"code":"783353","mask":"+_ (_____) _-__-__"},{"code":"783354","mask":"+_ (_____) _-__-__"},{"code":"783355","mask":"+_ (_____) _-__-__"},{"code":"783357","mask":"+_ (_____) _-__-__"},{"code":"783358","mask":"+_ (_____) _-__-__"},{"code":"783359","mask":"+_ (_____) _-__-__"},{"code":"783361","mask":"+_ (_____) _-__-__"},{"code":"783362","mask":"+_ (_____) _-__-__"},{"code":"783363","mask":"+_ (_____) _-__-__"},{"code":"783364","mask":"+_ (_____) _-__-__"},{"code":"783365","mask":"+_ (_____) _-__-__"},{"code":"783366","mask":"+_ (_____) _-__-__"},{"code":"783367","mask":"+_ (_____) _-__-__"},{"code":"783368","mask":"+_ (_____) _-__-__"},{"code":"783369","mask":"+_ (_____) _-__-__"},{"code":"783375","mask":"+_ (_____) _-__-__"},{"code":"7834","mask":"+_ (___) ___-__-__"},{"code":"78342","mask":"+_ (____) __-__-__"},{"code":"783431","mask":"+_ (_____) _-__-__"},{"code":"783432","mask":"+_ (_____) _-__-__"},{"code":"783433","mask":"+_ (_____) _-__-__"},{"code":"783434","mask":"+_ (_____) _-__-__"},{"code":"783436","mask":"+_ (_____) _-__-__"},{"code":"783437","mask":"+_ (_____) _-__-__"},{"code":"783438","mask":"+_ (_____) _-__-__"},{"code":"783439","mask":"+_ (_____) _-__-__"},{"code":"783441","mask":"+_ (_____) _-__-__"},{"code":"783442","mask":"+_ (_____) _-__-__"},{"code":"783443","mask":"+_ (_____) _-__-__"},{"code":"783444","mask":"+_ (_____) _-__-__"},{"code":"783445","mask":"+_ (_____) _-__-__"},{"code":"783446","mask":"+_ (_____) _-__-__"},{"code":"783447","mask":"+_ (_____) _-__-__"},{"code":"783448","mask":"+_ (_____) _-__-__"},{"code":"783449","mask":"+_ (_____) _-__-__"},{"code":"783451","mask":"+_ (_____) _-__-__"},{"code":"783453","mask":"+_ (_____) _-__-__"},{"code":"783454","mask":"+_ (_____) _-__-__"},{"code":"783456","mask":"+_ (_____) _-__-__"},{"code":"783457","mask":"+_ (_____) _-__-__"},{"code":"783458","mask":"+_ (_____) _-__-__"},{"code":"7835","mask":"+_ (___) ___-__-__"},{"code":"78352","mask":"+_ (____) __-__-__"},{"code":"783530","mask":"+_ (_____) _-__-__"},{"code":"783531","mask":"+_ (_____) _-__-__"},{"code":"783532","mask":"+_ (_____) _-__-__"},{"code":"783533","mask":"+_ (_____) _-__-__"},{"code":"783534","mask":"+_ (_____) _-__-__"},{"code":"783535","mask":"+_ (_____) _-__-__"},{"code":"783536","mask":"+_ (_____) _-__-__"},{"code":"783537","mask":"+_ (_____) _-__-__"},{"code":"783538","mask":"+_ (_____) _-__-__"},{"code":"783539","mask":"+_ (_____) _-__-__"},{"code":"783540","mask":"+_ (_____) _-__-__"},{"code":"783541","mask":"+_ (_____) _-__-__"},{"code":"783542","mask":"+_ (_____) _-__-__"},{"code":"783543","mask":"+_ (_____) _-__-__"},{"code":"783544","mask":"+_ (_____) _-__-__"},{"code":"783545","mask":"+_ (_____) _-__-__"},{"code":"783546","mask":"+_ (_____) _-__-__"},{"code":"783547","mask":"+_ (_____) _-__-__"},{"code":"783548","mask":"+_ (_____) _-__-__"},{"code":"783549","mask":"+_ (_____) _-__-__"},{"code":"7836","mask":"+_ (___) ___-__-__"},{"code":"78362","mask":"+_ (____) __-__-__"},{"code":"783631","mask":"+_ (_____) _-__-__"},{"code":"783632","mask":"+_ (_____) _-__-__"},{"code":"783633","mask":"+_ (_____) _-__-__"},{"code":"783635","mask":"+_ (_____) _-__-__"},{"code":"783636","mask":"+_ (_____) _-__-__"},{"code":"783637","mask":"+_ (_____) _-__-__"},{"code":"783638","mask":"+_ (_____) _-__-__"},{"code":"783639","mask":"+_ (_____) _-__-__"},{"code":"783641","mask":"+_ (_____) _-__-__"},{"code":"783643","mask":"+_ (_____) _-__-__"},{"code":"783644","mask":"+_ (_____) _-__-__"},{"code":"783645","mask":"+_ (_____) _-__-__"},{"code":"7840","mask":"+_ (___) ___-__-__"},{"code":"7841","mask":"+_ (___) ___-__-__"},{"code":"78412","mask":"+_ (____) __-__-__"},{"code":"784140","mask":"+_ (_____) _-__-__"},{"code":"784141","mask":"+_ (_____) _-__-__"},{"code":"784142","mask":"+_ (_____) _-__-__"},{"code":"784143","mask":"+_ (_____) _-__-__"},{"code":"784144","mask":"+_ (_____) _-__-__"},{"code":"784145","mask":"+_ (_____) _-__-__"},{"code":"784146","mask":"+_ (_____) _-__-__"},{"code":"784147","mask":"+_ (_____) _-__-__"},{"code":"784148","mask":"+_ (_____) _-__-__"},{"code":"784150","mask":"+_ (_____) _-__-__"},{"code":"784151","mask":"+_ (_____) _-__-__"},{"code":"784152","mask":"+_ (_____) _-__-__"},{"code":"784153","mask":"+_ (_____) _-__-__"},{"code":"784154","mask":"+_ (_____) _-__-__"},{"code":"784155","mask":"+_ (_____) _-__-__"},{"code":"784156","mask":"+_ (_____) _-__-__"},{"code":"784157","mask":"+_ (_____) _-__-__"},{"code":"784158","mask":"+_ (_____) _-__-__"},{"code":"784159","mask":"+_ (_____) _-__-__"},{"code":"784161","mask":"+_ (_____) _-__-__"},{"code":"784162","mask":"+_ (_____) _-__-__"},{"code":"784163","mask":"+_ (_____) _-__-__"},{"code":"784164","mask":"+_ (_____) _-__-__"},{"code":"784165","mask":"+_ (_____) _-__-__"},{"code":"784167","mask":"+_ (_____) _-__-__"},{"code":"784168","mask":"+_ (_____) _-__-__"},{"code":"784169","mask":"+_ (_____) _-__-__"},{"code":"7842","mask":"+_ (___) ___-__-__"},{"code":"78422","mask":"+_ (____) __-__-__"},{"code":"784230","mask":"+_ (_____) _-__-__"},{"code":"784231","mask":"+_ (_____) _-__-__"},{"code":"784232","mask":"+_ (_____) _-__-__"},{"code":"784233","mask":"+_ (_____) _-__-__"},{"code":"784234","mask":"+_ (_____) _-__-__"},{"code":"784235","mask":"+_ (_____) _-__-__"},{"code":"784237","mask":"+_ (_____) _-__-__"},{"code":"784238","mask":"+_ (_____) _-__-__"},{"code":"784239","mask":"+_ (_____) _-__-__"},{"code":"784240","mask":"+_ (_____) _-__-__"},{"code":"784241","mask":"+_ (_____) _-__-__"},{"code":"784242","mask":"+_ (_____) _-__-__"},{"code":"784243","mask":"+_ (_____) _-__-__"},{"code":"784244","mask":"+_ (_____) _-__-__"},{"code":"784245","mask":"+_ (_____) _-__-__"},{"code":"784246","mask":"+_ (_____) _-__-__"},{"code":"784247","mask":"+_ (_____) _-__-__"},{"code":"784248","mask":"+_ (_____) _-__-__"},{"code":"784249","mask":"+_ (_____) _-__-__"},{"code":"784253","mask":"+_ (_____) _-__-__"},{"code":"784254","mask":"+_ (_____) _-__-__"},{"code":"784255","mask":"+_ (_____) _-__-__"},{"code":"7843","mask":"+_ (___) ___-__-__"},{"code":"784341","mask":"+_ (_____) _-__-__"},{"code":"784342","mask":"+_ (_____) _-__-__"},{"code":"784344","mask":"+_ (_____) _-__-__"},{"code":"784345","mask":"+_ (_____) _-__-__"},{"code":"784346","mask":"+_ (_____) _-__-__"},{"code":"784348","mask":"+_ (_____) _-__-__"},{"code":"784360","mask":"+_ (_____) _-__-__"},{"code":"784361","mask":"+_ (_____) _-__-__"},{"code":"784362","mask":"+_ (_____) _-__-__"},{"code":"784364","mask":"+_ (_____) _-__-__"},{"code":"784365","mask":"+_ (_____) _-__-__"},{"code":"784366","mask":"+_ (_____) _-__-__"},{"code":"784367","mask":"+_ (_____) _-__-__"},{"code":"784368","mask":"+_ (_____) _-__-__"},{"code":"784369","mask":"+_ (_____) _-__-__"},{"code":"784370","mask":"+_ (_____) _-__-__"},{"code":"784371","mask":"+_ (_____) _-__-__"},{"code":"784373","mask":"+_ (_____) _-__-__"},{"code":"784374","mask":"+_ (_____) _-__-__"},{"code":"784375","mask":"+_ (_____) _-__-__"},{"code":"784376","mask":"+_ (_____) _-__-__"},{"code":"784377","mask":"+_ (_____) _-__-__"},{"code":"784378","mask":"+_ (_____) _-__-__"},{"code":"784379","mask":"+_ (_____) _-__-__"},{"code":"7844","mask":"+_ (___) ___-__-__"},{"code":"7845","mask":"+_ (___) ___-__-__"},{"code":"78452","mask":"+_ (____) __-__-__"},{"code":"784540","mask":"+_ (_____) _-__-__"},{"code":"784542","mask":"+_ (_____) _-__-__"},{"code":"784543","mask":"+_ (_____) _-__-__"},{"code":"784544","mask":"+_ (_____) _-__-__"},{"code":"784545","mask":"+_ (_____) _-__-__"},{"code":"784548","mask":"+_ (_____) _-__-__"},{"code":"784549","mask":"+_ (_____) _-__-__"},{"code":"784550","mask":"+_ (_____) _-__-__"},{"code":"784551","mask":"+_ (_____) _-__-__"},{"code":"784552","mask":"+_ (_____) _-__-__"},{"code":"784554","mask":"+_ (_____) _-__-__"},{"code":"784555","mask":"+_ (_____) _-__-__"},{"code":"784557","mask":"+_ (_____) _-__-__"},{"code":"784558","mask":"+_ (_____) _-__-__"},{"code":"784560","mask":"+_ (_____) _-__-__"},{"code":"784561","mask":"+_ (_____) _-__-__"},{"code":"784562","mask":"+_ (_____) _-__-__"},{"code":"784563","mask":"+_ (_____) _-__-__"},{"code":"784564","mask":"+_ (_____) _-__-__"},{"code":"784565","mask":"+_ (_____) _-__-__"},{"code":"784566","mask":"+_ (_____) _-__-__"},{"code":"784567","mask":"+_ (_____) _-__-__"},{"code":"784568","mask":"+_ (_____) _-__-__"},{"code":"784573","mask":"+_ (_____) _-__-__"},{"code":"784574","mask":"+_ (_____) _-__-__"},{"code":"784575","mask":"+_ (_____) _-__-__"},{"code":"784576","mask":"+_ (_____) _-__-__"},{"code":"784577","mask":"+_ (_____) _-__-__"},{"code":"784578","mask":"+_ (_____) _-__-__"},{"code":"784579","mask":"+_ (_____) _-__-__"},{"code":"784591","mask":"+_ (_____) _-__-__"},{"code":"784592","mask":"+_ (_____) _-__-__"},{"code":"784593","mask":"+_ (_____) _-__-__"},{"code":"784595","mask":"+_ (_____) _-__-__"},{"code":"784596","mask":"+_ (_____) _-__-__"},{"code":"7846","mask":"+_ (___) ___-__-__"},{"code":"78462","mask":"+_ (___) ___-__-__"},{"code":"784635","mask":"+_ (_____) _-__-__"},{"code":"784639","mask":"+_ (_____) _-__-__"},{"code":"784643","mask":"+_ (____) __-__-__"},{"code":"784646","mask":"+_ (_____) _-__-__"},{"code":"784647","mask":"+_ (_____) _-__-__"},{"code":"784650","mask":"+_ (_____) _-__-__"},{"code":"784651","mask":"+_ (_____) _-__-__"},{"code":"784652","mask":"+_ (_____) _-__-__"},{"code":"784653","mask":"+_ (_____) _-__-__"},{"code":"784654","mask":"+_ (_____) _-__-__"},{"code":"784655","mask":"+_ (_____) _-__-__"},{"code":"784656","mask":"+_ (_____) _-__-__"},{"code":"784657","mask":"+_ (_____) _-__-__"},{"code":"784660","mask":"+_ (_____) _-__-__"},{"code":"784661","mask":"+_ (_____) _-__-__"},{"code":"784663","mask":"+_ (_____) _-__-__"},{"code":"784667","mask":"+_ (_____) _-__-__"},{"code":"784670","mask":"+_ (_____) _-__-__"},{"code":"784671","mask":"+_ (_____) _-__-__"},{"code":"784672","mask":"+_ (_____) _-__-__"},{"code":"784673","mask":"+_ (_____) _-__-__"},{"code":"784674","mask":"+_ (_____) _-__-__"},{"code":"784675","mask":"+_ (_____) _-__-__"},{"code":"784676","mask":"+_ (_____) _-__-__"},{"code":"7847","mask":"+_ (___) ___-__-__"},{"code":"784722","mask":"+_ (_____) _-__-__"},{"code":"784731","mask":"+_ (_____) _-__-__"},{"code":"784732","mask":"+_ (_____) _-__-__"},{"code":"784733","mask":"+_ (_____) _-__-__"},{"code":"784735","mask":"+_ (_____) _-__-__"},{"code":"784736","mask":"+_ (_____) _-__-__"},{"code":"784741","mask":"+_ (_____) _-__-__"},{"code":"784742","mask":"+_ (_____) _-__-__"},{"code":"784743","mask":"+_ (_____) _-__-__"},{"code":"784744","mask":"+_ (_____) _-__-__"},{"code":"784745","mask":"+_ (_____) _-__-__"},{"code":"784746","mask":"+_ (_____) _-__-__"},{"code":"784747","mask":"+_ (_____) _-__-__"},{"code":"7848","mask":"+_ (___) ___-__-__"},{"code":"78482","mask":"+_ (____) __-__-__"},{"code":"7851","mask":"+_ (___) ___-__-__"},{"code":"78512","mask":"+_ (____) __-__-__"},{"code":"785171","mask":"+_ (_____) _-__-__"},{"code":"785172","mask":"+_ (_____) _-__-__"},{"code":"7855","mask":"+_ (___) ___-__-__"},{"code":"78552","mask":"+_ (____) __-__-__"},{"code":"78553","mask":"+_ (____) __-__-__"},{"code":"785549","mask":"+_ (_____) _-__-__"},{"code":"785551","mask":"+_ (_____) _-__-__"},{"code":"785552","mask":"+_ (_____) _-__-__"},{"code":"785555","mask":"+_ (_____) _-__-__"},{"code":"785556","mask":"+_ (_____) _-__-__"},{"code":"785557","mask":"+_ (_____) _-__-__"},{"code":"785558","mask":"+_ (_____) _-__-__"},{"code":"785559","mask":"+_ (_____) _-__-__"},{"code":"785563","mask":"+_ (_____) _-__-__"},{"code":"7861","mask":"+_ (___) ___-__-__"},{"code":"786130","mask":"+_ (_____) _-__-__"},{"code":"786131","mask":"+_ (_____) _-__-__"},{"code":"786132","mask":"+_ (_____) _-__-__"},{"code":"786133","mask":"+_ (_____) _-__-__"},{"code":"786135","mask":"+_ (_____) _-__-__"},{"code":"786137","mask":"+_ (_____) _-__-__"},{"code":"786138","mask":"+_ (_____) _-__-__"},{"code":"786140","mask":"+_ (_____) _-__-__"},{"code":"786141","mask":"+_ (_____) _-__-__"},{"code":"786142","mask":"+_ (_____) _-__-__"},{"code":"786143","mask":"+_ (_____) _-__-__"},{"code":"786144","mask":"+_ (_____) _-__-__"},{"code":"786145","mask":"+_ (_____) _-__-__"},{"code":"786146","mask":"+_ (_____) _-__-__"},{"code":"786147","mask":"+_ (_____) _-__-__"},{"code":"786148","mask":"+_ (_____) _-__-__"},{"code":"786149","mask":"+_ (_____) _-__-__"},{"code":"786150","mask":"+_ (_____) _-__-__"},{"code":"786151","mask":"+_ (_____) _-__-__"},{"code":"786152","mask":"+_ (_____) _-__-__"},{"code":"786153","mask":"+_ (_____) _-__-__"},{"code":"786154","mask":"+_ (_____) _-__-__"},{"code":"786155","mask":"+_ (_____) _-__-__"},{"code":"786156","mask":"+_ (_____) _-__-__"},{"code":"786157","mask":"+_ (_____) _-__-__"},{"code":"786158","mask":"+_ (_____) _-__-__"},{"code":"786159","mask":"+_ (_____) _-__-__"},{"code":"786160","mask":"+_ (_____) _-__-__"},{"code":"786161","mask":"+_ (_____) _-__-__"},{"code":"786162","mask":"+_ (_____) _-__-__"},{"code":"786163","mask":"+_ (_____) _-__-__"},{"code":"786164","mask":"+_ (_____) _-__-__"},{"code":"786165","mask":"+_ (_____) _-__-__"},{"code":"786166","mask":"+_ (_____) _-__-__"},{"code":"786167","mask":"+_ (_____) _-__-__"},{"code":"786168","mask":"+_ (_____) _-__-__"},{"code":"786169","mask":"+_ (_____) _-__-__"},{"code":"78617","mask":"+_ (____) __-__-__"},{"code":"786191","mask":"+_ (_____) _-__-__"},{"code":"786192","mask":"+_ (_____) _-__-__"},{"code":"786193","mask":"+_ (_____) _-__-__"},{"code":"786195","mask":"+_ (_____) _-__-__"},{"code":"786196","mask":"+_ (_____) _-__-__"},{"code":"7862","mask":"+_ (___) ___-__-__"},{"code":"78622","mask":"+_ (___) ___-__-__"},{"code":"7863","mask":"+_ (___) ___-__-__"},{"code":"78632","mask":"+_ (___) ___-__-__"},{"code":"786340","mask":"+_ (_____) _-__-__"},{"code":"786341","mask":"+_ (_____) _-__-__"},{"code":"786342","mask":"+_ (_____) _-__-__"},{"code":"786345","mask":"+_ (_____) _-__-__"},{"code":"786346","mask":"+_ (____) __-__-__"},{"code":"786347","mask":"+_ (_____) _-__-__"},{"code":"786348","mask":"+_ (_____) _-__-__"},{"code":"786349","mask":"+_ (_____) _-__-__"},{"code":"786350","mask":"+_ (_____) _-__-__"},{"code":"786351","mask":"+_ (_____) _-__-__"},{"code":"786352","mask":"+_ (____) __-__-__"},{"code":"786354","mask":"+_ (_____) _-__-__"},{"code":"786356","mask":"+_ (_____) _-__-__"},{"code":"786357","mask":"+_ (_____) _-__-__"},{"code":"786358","mask":"+_ (_____) _-__-__"},{"code":"786359","mask":"+_ (_____) _-__-__"},{"code":"786360","mask":"+_ (_____) _-__-__"},{"code":"786361","mask":"+_ (_____) _-__-__"},{"code":"786362","mask":"+_ (____) __-__-__"},{"code":"786365","mask":"+_ (_____) _-__-__"},{"code":"786368","mask":"+_ (_____) _-__-__"},{"code":"786369","mask":"+_ (_____) _-__-__"},{"code":"786370","mask":"+_ (_____) _-__-__"},{"code":"786371","mask":"+_ (_____) _-__-__"},{"code":"786372","mask":"+_ (_____) _-__-__"},{"code":"786373","mask":"+_ (_____) _-__-__"},{"code":"786374","mask":"+_ (_____) _-__-__"},{"code":"786375","mask":"+_ (_____) _-__-__"},{"code":"786376","mask":"+_ (_____) _-__-__"},{"code":"786377","mask":"+_ (_____) _-__-__"},{"code":"786378","mask":"+_ (_____) _-__-__"},{"code":"786379","mask":"+_ (_____) _-__-__"},{"code":"786391","mask":"+_ (_____) _-__-__"},{"code":"786392","mask":"+_ (____) __-__-__"},{"code":"786393","mask":"+_ (_____) _-__-__"},{"code":"786394","mask":"+_ (_____) _-__-__"},{"code":"786395","mask":"+_ (_____) _-__-__"},{"code":"786396","mask":"+_ (_____) _-__-__"},{"code":"786397","mask":"+_ (_____) _-__-__"},{"code":"7865","mask":"+_ (___) ___-__-__"},{"code":"78652","mask":"+_ (____) __-__-__"},{"code":"786540","mask":"+_ (_____) _-__-__"},{"code":"786541","mask":"+_ (_____) _-__-__"},{"code":"786542","mask":"+_ (_____) _-__-__"},{"code":"786543","mask":"+_ (_____) _-__-__"},{"code":"786544","mask":"+_ (_____) _-__-__"},{"code":"786545","mask":"+_ (_____) _-__-__"},{"code":"786547","mask":"+_ (_____) _-__-__"},{"code":"786548","mask":"+_ (_____) _-__-__"},{"code":"786549","mask":"+_ (_____) _-__-__"},{"code":"786552","mask":"+_ (_____) _-__-__"},{"code":"786554","mask":"+_ (_____) _-__-__"},{"code":"786555","mask":"+_ (_____) _-__-__"},{"code":"786556","mask":"+_ (_____) _-__-__"},{"code":"786557","mask":"+_ (_____) _-__-__"},{"code":"786558","mask":"+_ (_____) _-__-__"},{"code":"786559","mask":"+_ (_____) _-__-__"},{"code":"786560","mask":"+_ (_____) _-__-__"},{"code":"786563","mask":"+_ (_____) _-__-__"},{"code":"786565","mask":"+_ (_____) _-__-__"},{"code":"7866","mask":"+_ (___) ___-__-__"},{"code":"78662","mask":"+_ (____) __-__-__"},{"code":"786630","mask":"+_ (_____) _-__-__"},{"code":"786631","mask":"+_ (_____) _-__-__"},{"code":"786632","mask":"+_ (_____) _-__-__"},{"code":"786633","mask":"+_ (_____) _-__-__"},{"code":"786634","mask":"+_ (_____) _-__-__"},{"code":"786635","mask":"+_ (_____) _-__-__"},{"code":"786636","mask":"+_ (_____) _-__-__"},{"code":"786637","mask":"+_ (_____) _-__-__"},{"code":"786638","mask":"+_ (_____) _-__-__"},{"code":"7867","mask":"+_ (___) ___-__-__"},{"code":"78672","mask":"+_ (____) __-__-__"},{"code":"786731","mask":"+_ (_____) _-__-__"},{"code":"786732","mask":"+_ (_____) _-__-__"},{"code":"786733","mask":"+_ (_____) _-__-__"},{"code":"786734","mask":"+_ (_____) _-__-__"},{"code":"786735","mask":"+_ (_____) _-__-__"},{"code":"786736","mask":"+_ (_____) _-__-__"},{"code":"786737","mask":"+_ (_____) _-__-__"},{"code":"786738","mask":"+_ (_____) _-__-__"},{"code":"786739","mask":"+_ (_____) _-__-__"},{"code":"7871","mask":"+_ (___) ___-__-__"},{"code":"78712","mask":"+_ (____) __-__-__"},{"code":"787132","mask":"+_ (_____) _-__-__"},{"code":"787134","mask":"+_ (_____) _-__-__"},{"code":"787135","mask":"+_ (_____) _-__-__"},{"code":"787142","mask":"+_ (_____) _-__-__"},{"code":"787145","mask":"+_ (_____) _-__-__"},{"code":"787146","mask":"+_ (_____) _-__-__"},{"code":"787147","mask":"+_ (_____) _-__-__"},{"code":"7872","mask":"+_ (___) ___-__-__"},{"code":"78722","mask":"+_ (____) __-__-__"},{"code":"787236","mask":"+_ (_____) _-__-__"},{"code":"787239","mask":"+_ (_____) _-__-__"},{"code":"787240","mask":"+_ (_____) _-__-__"},{"code":"787262","mask":"+_ (_____) _-__-__"},{"code":"7873","mask":"+_ (___) ___-__-__"},{"code":"7877","mask":"+_ (___) ___-__-__"},{"code":"787770","mask":"+_ (_____) _-__-__"},{"code":"787771","mask":"+_ (_____) _-__-__"},{"code":"787772","mask":"+_ (_____) _-__-__"},{"code":"787773","mask":"+_ (_____) _-__-__"},{"code":"787777","mask":"+_ (_____) _-__-__"},{"code":"787778","mask":"+_ (_____) _-__-__"},{"code":"787779","mask":"+_ (_____) _-__-__"},{"code":"7878","mask":"+_ (___) ___-__-__"},{"code":"787870","mask":"+_ (_____) _-__-__"},{"code":"787875","mask":"+_ (_____) _-__-__"},{"code":"787876","mask":"+_ (_____) _-__-__"},{"code":"787877","mask":"+_ (_____) _-__-__"},{"code":"787878","mask":"+_ (_____) _-__-__"},{"code":"7879","mask":"+_ (___) ___-__-__"},{"code":"787922","mask":"+_ (_____) _-__-__"},{"code":"787934","mask":"+_ (_____) _-__-__"},{"code":"787935","mask":"+_ (_____) _-__-__"},{"code":"787937","mask":"+_ (_____) _-__-__"},{"code":"787961","mask":"+_ (_____) _-__-__"},{"code":"79","mask":"+_ (___) ___-__-__"}]